{
  "1740155264": [
    "W6YX",
    "14057.4",
    "KD0FNR/6",
    17,
    16,
    "1322z 30 Jan"
  ],
  "1740151372": [
    "W6YX",
    "14057.4",
    "KD0FNR/6",
    17,
    16,
    "1312z 30 Jan"
  ],
  "1740147525": [
    "W6YX",
    "14057.4",
    "KD0FNR/6",
    17,
    16,
    "1302z 30 Jan"
  ],
  "1740144213": [
    "W6YX",
    "14057.6",
    "KD0FNR/6",
    17,
    16,
    "1252z 30 Jan"
  ],
  "1739608367": [
    "WE9V",
    "14057.3",
    "KD0FNR/6",
    2,
    17,
    "1203z 29 Jan"
  ],
  "1739608036": [
    "N9CO",
    "14057.4",
    "KD0FNR/6",
    9,
    16,
    "1202z 29 Jan"
  ],
  "1739607028": [
    "W6YX",
    "14057.4",
    "KD0FNR/6",
    17,
    16,
    "1158z 29 Jan"
  ],
  "1739607023": [
    "K9IMM",
    "14057.4",
    "KD0FNR/6",
    4,
    16,
    "1158z 29 Jan"
  ],
  "1739605177": [
    "N9CO",
    "14057.4",
    "KD0FNR/6",
    5,
    16,
    "1152z 29 Jan"
  ],
  "1739604488": [
    "K9IMM",
    "14057.4",
    "KD0FNR/6",
    6,
    16,
    "1148z 29 Jan"
  ],
  "1739604477": [
    "W6YX",
    "14057.4",
    "KD0FNR/6",
    17,
    16,
    "1148z 29 Jan"
  ],
  "1739604273": [
    "W8WWV",
    "14057.4",
    "KD0FNR/6",
    2,
    16,
    "1147z 29 Jan"
  ],
  "1739602724": [
    "N9CO",
    "14057.5",
    "KD0FNR/6",
    2,
    16,
    "1142z 29 Jan"
  ],
  "1739601769": [
    "K9IMM",
    "14057.6",
    "KD0FNR/6",
    10,
    16,
    "1137z 29 Jan"
  ],
  "1739601750": [
    "W6YX",
    "14057.6",
    "KD0FNR/6",
    17,
    16,
    "1137z 29 Jan"
  ],
  "1737820576": [
    "W6YX",
    "14057.4",
    "KD0FNR/6",
    15,
    16,
    "0407z 28 Jan"
  ],
  "1737804525": [
    "W6YX",
    "14057.4",
    "KD0FNR/6",
    15,
    16,
    "0356z 28 Jan"
  ],
  "1737789157": [
    "W6YX",
    "14057.4",
    "KD0FNR/6",
    15,
    16,
    "0346z 28 Jan"
  ],
  "1737773574": [
    "W6YX",
    "14057.6",
    "KD0FNR/6",
    15,
    16,
    "0336z 28 Jan"
  ],
  "1736389709": [
    "AC0C-1",
    "14057.4",
    "KD0FNR/6",
    3,
    16,
    "1445z 27 Jan"
  ],
  "1736389558": [
    "K3PA-1",
    "14057.4",
    "KD0FNR/6",
    4,
    16,
    "1445z 27 Jan"
  ],
  "1736388244": [
    "W3OA",
    "14057.4",
    "KD0FNR/6",
    2,
    17,
    "1444z 27 Jan"
  ],
  "1736386353": [
    "W8WWV",
    "14057.4",
    "KD0FNR/6",
    6,
    16,
    "1443z 27 Jan"
  ],
  "1736381464": [
    "W6YX",
    "14057.4",
    "KD0FNR/6",
    16,
    16,
    "1439z 27 Jan"
  ],
  "1736374573": [
    "K3PA-1",
    "14057.4",
    "KD0FNR/6",
    7,
    17,
    "1434z 27 Jan"
  ],
  "1736370606": [
    "W3OA",
    "14057.4",
    "KD0FNR/6",
    2,
    16,
    "1431z 27 Jan"
  ],
  "1736370167": [
    "W8WWV",
    "14057.4",
    "KD0FNR/6",
    8,
    16,
    "1431z 27 Jan"
  ],
  "1736368162": [
    "AC0C-1",
    "14057.4",
    "KD0FNR/6",
    3,
    16,
    "1429z 27 Jan"
  ],
  "1736367664": [
    "W6YX",
    "14057.4",
    "KD0FNR/6",
    17,
    16,
    "1429z 27 Jan"
  ],
  "1736360981": [
    "W8WWV",
    "14057.5",
    "KD0FNR/6",
    4,
    17,
    "1424z 27 Jan"
  ],
  "1736360307": [
    "K3PA-1",
    "14057.5",
    "KD0FNR/6",
    2,
    16,
    "1423z 27 Jan"
  ],
  "1736356973": [
    "W3OA",
    "14057.5",
    "KD0FNR/6",
    2,
    16,
    "1421z 27 Jan"
  ],
  "1736356065": [
    "W1NT-2",
    "14057.6",
    "KD0FNR/6",
    2,
    16,
    "1420z 27 Jan"
  ],
  "1736354291": [
    "W6YX",
    "14057.6",
    "KD0FNR/6",
    17,
    16,
    "1419z 27 Jan"
  ],
  "1736215733": [
    "W8WWV",
    "14057.4",
    "KD0FNR/6",
    9,
    16,
    "1215z 27 Jan"
  ],
  "1736215688": [
    "W6YX",
    "14057.4",
    "KD0FNR/6",
    17,
    16,
    "1215z 27 Jan"
  ],
  "1736191325": [
    "W8WWV",
    "14057.4",
    "KD0FNR/6",
    14,
    16,
    "1152z 27 Jan"
  ],
  "1736191258": [
    "W6YX",
    "14057.4",
    "KD0FNR/6",
    17,
    16,
    "1152z 27 Jan"
  ],
  "1736184197": [
    "W3OA",
    "14057.4",
    "KD0FNR/6",
    6,
    16,
    "1145z 27 Jan"
  ],
  "1736181982": [
    "W6YX",
    "14057.4",
    "KD0FNR/6",
    17,
    16,
    "1142z 27 Jan"
  ],
  "1736181877": [
    "W8WWV",
    "14057.4",
    "KD0FNR/6",
    13,
    16,
    "1142z 27 Jan"
  ],
  "1736175807": [
    "K7EK",
    "14057.5",
    "KD0FNR/6",
    11,
    16,
    "1136z 27 Jan"
  ],
  "1736172135": [
    "W6YX",
    "14057.6",
    "KD0FNR/6",
    16,
    16,
    "1132z 27 Jan"
  ],
  "1736172103": [
    "W3OA",
    "14057.6",
    "KD0FNR/6",
    4,
    16,
    "1132z 27 Jan"
  ],
  "1736172029": [
    "W8WWV",
    "14057.5",
    "KD0FNR/6",
    15,
    16,
    "1132z 27 Jan"
  ],
  "1734977290": [
    "K9IMM",
    "28057.5",
    "KD0FNR/6",
    24,
    14,
    "1613z 26 Jan"
  ],
  "1734977236": [
    "W6YX",
    "28057.4",
    "KD0FNR/6",
    23,
    14,
    "1613z 26 Jan"
  ],
  "1734977188": [
    "WE9V",
    "28057.4",
    "KD0FNR/6",
    8,
    13,
    "1613z 26 Jan"
  ],
  "1734975988": [
    "N9CO",
    "28057.5",
    "KD0FNR/6",
    14,
    15,
    "1610z 26 Jan"
  ],
  "1734975832": [
    "ZF9CW",
    "28057.5",
    "KD0FNR/6",
    15,
    16,
    "1610z 26 Jan"
  ],
  "1734974372": [
    "F8DGY",
    "28057.5",
    "KD0FNR/6",
    9,
    16,
    "1607z 26 Jan"
  ],
  "1734974206": [
    "DL0LA",
    "28057.5",
    "KD0FNR/6",
    13,
    15,
    "1607z 26 Jan"
  ],
  "1734973311": [
    "S53A",
    "28057.5",
    "KD0FNR/6",
    8,
    15,
    "1606z 26 Jan"
  ],
  "1734973307": [
    "TI7W",
    "28057.5",
    "KD0FNR/6",
    17,
    19,
    "1606z 26 Jan"
  ],
  "1734972737": [
    "OE9GHV",
    "28057.5",
    "KD0FNR/6",
    7,
    15,
    "1605z 26 Jan"
  ],
  "1734884461": [
    "KO7SS",
    "14057.4",
    "KD0FNR/6",
    6,
    17,
    "1343z 26 Jan"
  ],
  "1734882936": [
    "W6YX",
    "14057.4",
    "KD0FNR/6",
    15,
    16,
    "1339z 26 Jan"
  ],
  "1734880280": [
    "KO7SS",
    "14057.4",
    "KD0FNR/6",
    5,
    16,
    "1332z 26 Jan"
  ],
  "1734879172": [
    "W6YX",
    "14057.4",
    "KD0FNR/6",
    15,
    16,
    "1329z 26 Jan"
  ],
  "1734860986": [
    "W6YX",
    "14057.5",
    "KD0FNR/6",
    15,
    16,
    "1225z 26 Jan"
  ],
  "1734849252": [
    "W6YX",
    "14057.4",
    "KD0FNR/6",
    17,
    16,
    "1142z 26 Jan"
  ],
  "1734846353": [
    "W6YX",
    "14057.6",
    "KD0FNR/6",
    17,
    16,
    "1132z 26 Jan"
  ],
  "1734654418": [
    "N9CO",
    "28056.0",
    "KD0FNR/6",
    12,
    16,
    "2155z 25 Jan"
  ],
  "1734654406": [
    "K3PA-1",
    "28056.3",
    "KD0FNR/6",
    32,
    15,
    "2155z 25 Jan"
  ],
  "1734654405": [
    "K3PA-1",
    "28056.0",
    "KD0FNR/6",
    27,
    15,
    "2155z 25 Jan"
  ],
  "1734654403": [
    "NJ4P",
    "28056.0",
    "KD0FNR/6",
    9,
    15,
    "2155z 25 Jan"
  ],
  "1734654401": [
    "AC0C-1",
    "28056.0",
    "KD0FNR/6",
    11,
    15,
    "2155z 25 Jan"
  ],
  "1734654398": [
    "KM3T-3",
    "28056.0",
    "KD0FNR/6",
    14,
    16,
    "2155z 25 Jan"
  ],
  "1734654396": [
    "W6YX",
    "28056.0",
    "KD0FNR/6",
    19,
    16,
    "2155z 25 Jan"
  ],
  "1734654394": [
    "KM3T",
    "28056.0",
    "KD0FNR/6",
    15,
    15,
    "2155z 25 Jan"
  ],
  "1734654392": [
    "ZF9CW",
    "28056.0",
    "KD0FNR/6",
    37,
    15,
    "2155z 25 Jan"
  ],
  "1734654386": [
    "KM3T-2",
    "28056.0",
    "KD0FNR/6",
    14,
    15,
    "2155z 25 Jan"
  ],
  "1734653054": [
    "KP3CW",
    "28056.0",
    "KD0FNR/6",
    5,
    15,
    "2151z 25 Jan"
  ],
  "1734652821": [
    "W8WWV",
    "28055.9",
    "KD0FNR/6",
    6,
    15,
    "2150z 25 Jan"
  ],
  "1734652663": [
    "TI7W",
    "28056.0",
    "KD0FNR/6",
    15,
    19,
    "2149z 25 Jan"
  ],
  "1734651740": [
    "KM3T",
    "28056.0",
    "KD0FNR/6",
    11,
    15,
    "2146z 25 Jan"
  ],
  "1734651685": [
    "WC2L",
    "28056.0",
    "KD0FNR/6",
    11,
    16,
    "2146z 25 Jan"
  ],
  "1734651483": [
    "VE6JY",
    "28056.0",
    "KD0FNR/6",
    8,
    15,
    "2145z 25 Jan"
  ],
  "1734651309": [
    "NJ4P",
    "28056.0",
    "KD0FNR/6",
    5,
    16,
    "2145z 25 Jan"
  ],
  "1734651266": [
    "K9IMM",
    "28056.0",
    "KD0FNR/6",
    15,
    15,
    "2145z 25 Jan"
  ],
  "1734651099": [
    "W1NT-2",
    "28056.0",
    "KD0FNR/6",
    6,
    15,
    "2144z 25 Jan"
  ],
  "1734651072": [
    "ZF9CW",
    "28056.0",
    "KD0FNR/6",
    13,
    16,
    "2144z 25 Jan"
  ],
  "1734651026": [
    "W2NAF",
    "28056.0",
    "KD0FNR/6",
    15,
    15,
    "2144z 25 Jan"
  ],
  "1734650995": [
    "WZ7I",
    "28056.0",
    "KD0FNR/6",
    9,
    15,
    "2144z 25 Jan"
  ],
  "1734650885": [
    "KM3T-3",
    "28056.0",
    "KD0FNR/6",
    12,
    16,
    "2143z 25 Jan"
  ],
  "1734650880": [
    "N9CO",
    "28056.0",
    "KD0FNR/6",
    11,
    15,
    "2143z 25 Jan"
  ],
  "1734650870": [
    "K3PA-1",
    "28056.3",
    "KD0FNR/6",
    26,
    15,
    "2143z 25 Jan"
  ],
  "1734650869": [
    "K3PA-1",
    "28056.0",
    "KD0FNR/6",
    24,
    15,
    "2143z 25 Jan"
  ],
  "1734650863": [
    "KM3T-2",
    "28056.0",
    "KD0FNR/6",
    12,
    15,
    "2143z 25 Jan"
  ],
  "1734650858": [
    "WB6BEE",
    "28056.0",
    "KD0FNR/6",
    16,
    16,
    "2143z 25 Jan"
  ],
  "1734650857": [
    "AC0C-1",
    "28056.0",
    "KD0FNR/6",
    10,
    16,
    "2143z 25 Jan"
  ],
  "1734650856": [
    "W6YX",
    "28056.0",
    "KD0FNR/6",
    12,
    16,
    "2143z 25 Jan"
  ],
  "1734646221": [
    "TI7W",
    "28057.5",
    "KD0FNR/6",
    13,
    19,
    "2128z 25 Jan"
  ],
  "1734646219": [
    "N9CO",
    "28057.5",
    "KD0FNR/6",
    8,
    15,
    "2128z 25 Jan"
  ],
  "1734646038": [
    "WC2L",
    "28057.5",
    "KD0FNR/6",
    14,
    16,
    "2127z 25 Jan"
  ],
  "1734646019": [
    "K3PA-1",
    "28057.8",
    "KD0FNR/6",
    32,
    16,
    "2127z 25 Jan"
  ],
  "1734646003": [
    "PJ2A",
    "28057.5",
    "KD0FNR/6",
    3,
    15,
    "2127z 25 Jan"
  ],
  "1734645986": [
    "KM3T-2",
    "28057.5",
    "KD0FNR/6",
    16,
    16,
    "2127z 25 Jan"
  ],
  "1734645830": [
    "K3PA-1",
    "28057.5",
    "KD0FNR/6",
    31,
    16,
    "2126z 25 Jan"
  ],
  "1734645828": [
    "W1NT-2",
    "28057.5",
    "KD0FNR/6",
    8,
    15,
    "2126z 25 Jan"
  ]
,
  "1740297161": [
    "W2NAF",
    "28054.0",
    "K3Y/6",
    10,
    13,
    "1821z 30 Jan"
  ],
  "1740296347": [
    "KH6LC",
    "28054.0",
    "K3Y/6",
    19,
    12,
    "1819z 30 Jan"
  ],
  "1740295991": [
    "K1RA",
    "28054.0",
    "K3Y/6",
    16,
    12,
    "1819z 30 Jan"
  ],
  "1740295889": [
    "PJ2A",
    "28054.0",
    "K3Y/6",
    7,
    11,
    "1818z 30 Jan"
  ],
  "1740295877": [
    "WZ7I",
    "28054.0",
    "K3Y/6",
    20,
    12,
    "1818z 30 Jan"
  ],
  "1740295602": [
    "N4ZR",
    "28054.0",
    "K3Y/6",
    26,
    11,
    "1818z 30 Jan"
  ],
  "1740295527": [
    "WE9V",
    "28053.9",
    "K3Y/6",
    16,
    12,
    "1818z 30 Jan"
  ],
  "1740295522": [
    "KM3T-3",
    "28054.0",
    "K3Y/6",
    12,
    12,
    "1818z 30 Jan"
  ],
  "1740295478": [
    "KM3T",
    "28054.0",
    "K3Y/6",
    12,
    12,
    "1818z 30 Jan"
  ],
  "1740295472": [
    "TI7W",
    "28054.0",
    "K3Y/6",
    20,
    14,
    "1818z 30 Jan"
  ],
  "1740295448": [
    "AC0C-1",
    "28054.0",
    "K3Y/6",
    29,
    12,
    "1818z 30 Jan"
  ],
  "1740295155": [
    "W1NT-2",
    "28054.0",
    "K3Y/6",
    14,
    12,
    "1817z 30 Jan"
  ],
  "1740295140": [
    "W8WWV",
    "28053.9",
    "K3Y/6",
    10,
    12,
    "1817z 30 Jan"
  ],
  "1740295133": [
    "KM3T-2",
    "28054.0",
    "K3Y/6",
    15,
    12,
    "1817z 30 Jan"
  ],
  "1740295131": [
    "K9IMM",
    "28054.0",
    "K3Y/6",
    20,
    12,
    "1817z 30 Jan"
  ],
  "1740295128": [
    "VE6JY",
    "28054.0",
    "K3Y/6",
    28,
    12,
    "1817z 30 Jan"
  ],
  "1740294548": [
    "N9CO",
    "28054.0",
    "K3Y/6",
    14,
    12,
    "1816z 30 Jan"
  ],
  "1740294532": [
    "W8WTS",
    "28053.9",
    "K3Y/6",
    11,
    11,
    "1816z 30 Jan"
  ],
  "1740294522": [
    "K3PA-1",
    "28054.0",
    "K3Y/6",
    38,
    12,
    "1816z 30 Jan"
  ],
  "1740294521": [
    "K3PA-1",
    "28054.3",
    "K3Y/6",
    47,
    12,
    "1816z 30 Jan"
  ],
  "1740292133": [
    "W2NAF",
    "28054.0",
    "K3Y/6",
    12,
    12,
    "1810z 30 Jan"
  ],
  "1740291853": [
    "KH6LC",
    "28054.0",
    "K3Y/6",
    6,
    11,
    "1809z 30 Jan"
  ],
  "1740291548": [
    "TI7W",
    "28054.0",
    "K3Y/6",
    24,
    13,
    "1808z 30 Jan"
  ],
  "1740291145": [
    "KM3T",
    "28054.0",
    "K3Y/6",
    17,
    12,
    "1808z 30 Jan"
  ],
  "1740291144": [
    "N4ZR",
    "28054.0",
    "K3Y/6",
    9,
    12,
    "1808z 30 Jan"
  ],
  "1740291141": [
    "K3PA-1",
    "28054.0",
    "K3Y/6",
    42,
    12,
    "1808z 30 Jan"
  ],
  "1740291138": [
    "K3PA-1",
    "28054.3",
    "K3Y/6",
    53,
    12,
    "1808z 30 Jan"
  ],
  "1740291126": [
    "PJ2A",
    "28054.0",
    "K3Y/6",
    10,
    12,
    "1808z 30 Jan"
  ],
  "1740291124": [
    "AC0C-1",
    "28054.0",
    "K3Y/6",
    27,
    12,
    "1808z 30 Jan"
  ],
  "1740291122": [
    "ZF9CW",
    "28054.0",
    "K3Y/6",
    25,
    12,
    "1808z 30 Jan"
  ],
  "1740291121": [
    "N9CO",
    "28054.0",
    "K3Y/6",
    12,
    12,
    "1808z 30 Jan"
  ],
  "1740291117": [
    "WE9V",
    "28053.9",
    "K3Y/6",
    14,
    12,
    "1808z 30 Jan"
  ],
  "1740291114": [
    "DC8YZ",
    "28054.0",
    "K3Y/6",
    10,
    12,
    "1808z 30 Jan"
  ],
  "1740291110": [
    "W1NT-2",
    "28054.0",
    "K3Y/6",
    14,
    12,
    "1808z 30 Jan"
  ],
  "1740291108": [
    "WZ7I",
    "28054.0",
    "K3Y/6",
    22,
    12,
    "1808z 30 Jan"
  ],
  "1740291105": [
    "KM3T-2",
    "28054.0",
    "K3Y/6",
    19,
    12,
    "1808z 30 Jan"
  ],
  "1740291100": [
    "K9IMM",
    "28054.0",
    "K3Y/6",
    19,
    12,
    "1808z 30 Jan"
  ],
  "1740291094": [
    "KM3T-3",
    "28054.0",
    "K3Y/6",
    15,
    12,
    "1808z 30 Jan"
  ],
  "1740013048": [
    "NG7M",
    "3554.0",
    "K3Y/6",
    5,
    13,
    "0500z 30 Jan"
  ],
  "1740012352": [
    "ND7K",
    "3554.0",
    "K3Y/6",
    12,
    13,
    "0457z 30 Jan"
  ],
  "1740012283": [
    "K2PO/7",
    "3554.0",
    "K3Y/6",
    15,
    13,
    "0456z 30 Jan"
  ],
  "1740012251": [
    "WA7LNW",
    "3554.0",
    "K3Y/6",
    25,
    14,
    "0456z 30 Jan"
  ],
  "1740012214": [
    "W6YX",
    "3554.0",
    "K3Y/6",
    12,
    14,
    "0456z 30 Jan"
  ],
  "1740012201": [
    "NT6Q",
    "3554.0",
    "K3Y/6",
    25,
    14,
    "0456z 30 Jan"
  ],
  "1740011933": [
    "N6TV",
    "3554.0",
    "K3Y/6",
    19,
    15,
    "0454z 30 Jan"
  ],
  "1740011916": [
    "K6FOD",
    "3554.0",
    "K3Y/6",
    12,
    15,
    "0454z 30 Jan"
  ],
  "1740011783": [
    "WF7U",
    "3554.0",
    "K3Y/6",
    24,
    17,
    "0453z 30 Jan"
  ],
  "1740011779": [
    "KO7SS",
    "3554.0",
    "K3Y/6",
    9,
    17,
    "0453z 30 Jan"
  ],
  "1740011275": [
    "NG7M",
    "3554.0",
    "K3Y/6",
    18,
    15,
    "0449z 30 Jan"
  ],
  "1740010484": [
    "ND7K",
    "3554.0",
    "K3Y/6",
    11,
    15,
    "0446z 30 Jan"
  ],
  "1740010468": [
    "WA7LNW",
    "3554.0",
    "K3Y/6",
    20,
    15,
    "0446z 30 Jan"
  ],
  "1740010409": [
    "N6TV",
    "3554.0",
    "K3Y/6",
    15,
    14,
    "0445z 30 Jan"
  ],
  "1740010403": [
    "K6FOD",
    "3554.0",
    "K3Y/6",
    12,
    15,
    "0445z 30 Jan"
  ],
  "1740010397": [
    "NT6Q",
    "3554.0",
    "K3Y/6",
    20,
    15,
    "0445z 30 Jan"
  ],
  "1740010393": [
    "W6YX",
    "3554.0",
    "K3Y/6",
    15,
    15,
    "0445z 30 Jan"
  ],
  "1740010389": [
    "K2PO/7",
    "3554.0",
    "K3Y/6",
    19,
    15,
    "0445z 30 Jan"
  ],
  "1740009700": [
    "W6YX",
    "7054.0",
    "K3Y/6",
    16,
    16,
    "0441z 30 Jan"
  ],
  "1740009697": [
    "WE9V",
    "7054.0",
    "K3Y/6",
    13,
    16,
    "0441z 30 Jan"
  ],
  "1740009541": [
    "NJ4P",
    "7054.0",
    "K3Y/6",
    6,
    14,
    "0439z 30 Jan"
  ],
  "1740009538": [
    "WA7LNW",
    "7054.0",
    "K3Y/6",
    17,
    13,
    "0439z 30 Jan"
  ],
  "1740009534": [
    "KL7RA",
    "7054.0",
    "K3Y/6",
    38,
    14,
    "0439z 30 Jan"
  ],
  "1740009500": [
    "K2PO/7",
    "7054.0",
    "K3Y/6",
    21,
    15,
    "0439z 30 Jan"
  ],
  "1740008977": [
    "KM3T",
    "7054.0",
    "K3Y/6",
    9,
    13,
    "0437z 30 Jan"
  ],
  "1740008972": [
    "NG7M",
    "7054.0",
    "K3Y/6",
    7,
    13,
    "0437z 30 Jan"
  ],
  "1740008861": [
    "W1NT-6",
    "7054.0",
    "K3Y/6",
    14,
    12,
    "0436z 30 Jan"
  ],
  "1740008858": [
    "K9IMM",
    "7054.0",
    "K3Y/6",
    17,
    11,
    "0436z 30 Jan"
  ],
  "1740008373": [
    "VE6WZ",
    "7054.1",
    "K3Y/6",
    20,
    12,
    "0433z 30 Jan"
  ],
  "1740008371": [
    "KM3T-3",
    "7054.0",
    "K3Y/6",
    13,
    13,
    "0433z 30 Jan"
  ],
  "1740008362": [
    "N8DXE",
    "7054.0",
    "K3Y/6",
    8,
    13,
    "0433z 30 Jan"
  ],
  "1740008360": [
    "W2MV",
    "7054.0",
    "K3Y/6",
    27,
    13,
    "0433z 30 Jan"
  ],
  "1740008359": [
    "KM3T",
    "7054.0",
    "K3Y/6",
    13,
    13,
    "0433z 30 Jan"
  ],
  "1740008191": [
    "VE7CC",
    "7054.0",
    "K3Y/6",
    6,
    12,
    "0433z 30 Jan"
  ],
  "1740007902": [
    "K5EM",
    "7054.0",
    "K3Y/6",
    19,
    13,
    "0429z 30 Jan"
  ],
  "1740007900": [
    "WE9V",
    "7054.0",
    "K3Y/6",
    16,
    13,
    "0429z 30 Jan"
  ],
  "1740007898": [
    "W1NT-2",
    "7054.0",
    "K3Y/6",
    27,
    13,
    "0429z 30 Jan"
  ],
  "1740007894": [
    "W6YX",
    "7054.0",
    "K3Y/6",
    15,
    13,
    "0429z 30 Jan"
  ],
  "1740007893": [
    "N9CO",
    "7054.0",
    "K3Y/6",
    19,
    13,
    "0429z 30 Jan"
  ],
  "1740007890": [
    "K2PO/7",
    "7054.0",
    "K3Y/6",
    17,
    13,
    "0429z 30 Jan"
  ],
  "1740007886": [
    "WA7LNW",
    "7054.0",
    "K3Y/6",
    23,
    13,
    "0429z 30 Jan"
  ],
  "1740007872": [
    "W2NAF",
    "7054.0",
    "K3Y/6",
    23,
    13,
    "0429z 30 Jan"
  ],
  "1740007868": [
    "KL7RA",
    "7054.0",
    "K3Y/6",
    26,
    13,
    "0429z 30 Jan"
  ],
  "1740007271": [
    "WC2L",
    "7054.0",
    "K3Y/6",
    8,
    13,
    "0424z 30 Jan"
  ],
  "1740006882": [
    "W3DAN",
    "7054.0",
    "K3Y/6",
    12,
    14,
    "0423z 30 Jan"
  ],
  "1740006878": [
    "W2MV",
    "7054.0",
    "K3Y/6",
    12,
    14,
    "0423z 30 Jan"
  ],
  "1740006874": [
    "VE6WZ",
    "7054.1",
    "K3Y/6",
    12,
    14,
    "0423z 30 Jan"
  ],
  "1740006872": [
    "WF7U",
    "7054.0",
    "K3Y/6",
    16,
    13,
    "0423z 30 Jan"
  ],
  "1740006848": [
    "N8DXE",
    "7054.0",
    "K3Y/6",
    11,
    14,
    "0423z 30 Jan"
  ],
  "1740006783": [
    "NT6Q",
    "7054.0",
    "K3Y/6",
    20,
    14,
    "0422z 30 Jan"
  ],
  "1740006774": [
    "WZ7I",
    "7054.0",
    "K3Y/6",
    14,
    14,
    "0422z 30 Jan"
  ],
  "1740006767": [
    "W1NT-6",
    "7054.0",
    "K3Y/6",
    15,
    14,
    "0421z 30 Jan"
  ],
  "1740006735": [
    "VE7CC",
    "7054.0",
    "K3Y/6",
    8,
    14,
    "0421z 30 Jan"
  ],
  "1740006722": [
    "ND7K",
    "7054.0",
    "K3Y/6",
    21,
    14,
    "0421z 30 Jan"
  ],
  "1740006256": [
    "K3LR",
    "7054.0",
    "K3Y/6",
    20,
    15,
    "0418z 30 Jan"
  ],
  "1740006184": [
    "KM3T-2",
    "7054.0",
    "K3Y/6",
    30,
    13,
    "0418z 30 Jan"
  ],
  "1740005999": [
    "WA7LNW",
    "7054.0",
    "K3Y/6",
    17,
    14,
    "0416z 30 Jan"
  ],
  "1740005992": [
    "N9CO",
    "7054.0",
    "K3Y/6",
    19,
    14,
    "0416z 30 Jan"
  ],
  "1740005991": [
    "W6YX",
    "7054.0",
    "K3Y/6",
    15,
    14,
    "0416z 30 Jan"
  ],
  "1740005990": [
    "K5EM",
    "7054.0",
    "K3Y/6",
    25,
    14,
    "0416z 30 Jan"
  ],
  "1740005989": [
    "NG7M",
    "7054.0",
    "K3Y/6",
    6,
    14,
    "0416z 30 Jan"
  ],
  "1740005986": [
    "K9IMM",
    "7054.0",
    "K3Y/6",
    17,
    14,
    "0416z 30 Jan"
  ]
,
  "1737793363": [
    "W6YX",
    "7039.0",
    "KO6BLZ",
    8,
    20,
    "0349z 28 Jan"
  ],
  "1734678951": [
    "K7RUT",
    "21039.9",
    "KO6BP",
    23,
    10,
    "2321z 25 Jan"
  ],
  "1734232108": [
    "W6YX",
    "3550.0",
    "KO6BPT",
    22,
    13,
    "2316z 24 Jan"
  ],
  "1733989884": [
    "W6YX",
    "28056.0",
    "KO6BTY",
    28,
    16,
    "1422z 24 Jan"
  ],
  "1733758621": [
    "W6YX",
    "3580.0",
    "KO6BPT",
    37,
    11,
    "0029z 24 Jan"
  ],
  "1733622258": [
    "WB6BEE",
    "28056.0",
    "KO6BTY",
    10,
    15,
    "1629z 23 Jan"
  ],
  "1733622238": [
    "W6YX",
    "28055.9",
    "KO6BTY",
    22,
    16,
    "1629z 23 Jan"
  ],
  "1731137782": [
    "W1NT-2",
    "28057.5",
    "KO6BTY",
    6,
    16,
    "1808z 20 Jan"
  ],
  "1731133759": [
    "W6YX",
    "28057.5",
    "KO6BTY",
    18,
    16,
    "1806z 20 Jan"
  ],
  "1729907176": [
    "CX6VM",
    "28057.4",
    "KO6BTY",
    4,
    16,
    "1718z 19 Jan"
  ],
  "1729905434": [
    "KM3T-3",
    "28057.5",
    "KO6BT",
    11,
    16,
    "1714z 19 Jan"
  ],
  "1729904930": [
    "W6YX",
    "28057.5",
    "KO6BTY",
    18,
    15,
    "1713z 19 Jan"
  ],
  "1729582992": [
    "W6YX",
    "28057.5",
    "KO6BTY",
    18,
    16,
    "0104z 19 Jan"
  ],
  "1729579457": [
    "W6YX",
    "28057.5",
    "KO6BTY",
    11,
    15,
    "0046z 19 Jan"
  ],
  "1727475076": [
    "W2NAF",
    "28058.0",
    "KO6BTY/6",
    9,
    15,
    "2154z 14 Jan"
  ],
  "1727475069": [
    "AC0C-1",
    "28058.0",
    "KO6BTY/6",
    10,
    16,
    "2154z 14 Jan"
  ],
  "1727475057": [
    "WB6BEE",
    "28058.0",
    "KO6BTY/6",
    16,
    16,
    "2154z 14 Jan"
  ],
  "1727475054": [
    "W1NT-2",
    "28058.0",
    "KO6BTY/6",
    11,
    15,
    "2154z 14 Jan"
  ],
  "1727474877": [
    "WC2L",
    "28058.0",
    "KO6BT",
    11,
    16,
    "2154z 14 Jan"
  ],
  "1727474760": [
    "WZ7I",
    "28058.0",
    "KO6BT",
    7,
    15,
    "2154z 14 Jan"
  ],
  "1727473460": [
    "W6YX",
    "28058.0",
    "KO6BTY/6",
    13,
    15,
    "2151z 14 Jan"
  ],
  "1727340546": [
    "WE9V",
    "28069.9",
    "KO6BTY",
    12,
    15,
    "1622z 14 Jan"
  ],
  "1727340502": [
    "N9CO",
    "28070.0",
    "KO6BTY",
    22,
    16,
    "1621z 14 Jan"
  ],
  "1727340490": [
    "K9IMM",
    "28070.0",
    "KO6BTY",
    24,
    16,
    "1621z 14 Jan"
  ],
  "1727340467": [
    "W6YX",
    "28070.0",
    "KO6BTY",
    21,
    16,
    "1621z 14 Jan"
  ],
  "1727339060": [
    "TI7W",
    "28070.0",
    "KO6BT",
    6,
    16,
    "1619z 14 Jan"
  ],
  "1727339019": [
    "W1NT-6",
    "28070.0",
    "KO6BTY",
    5,
    15,
    "1619z 14 Jan"
  ],
  "1727336764": [
    "TI7W",
    "28070.0",
    "KO6BTY",
    6,
    16,
    "1616z 14 Jan"
  ],
  "1727336411": [
    "KM3T-3",
    "28070.0",
    "KO6BTY",
    8,
    16,
    "1615z 14 Jan"
  ],
  "1727334446": [
    "W6YX",
    "28070.0",
    "KO6BTY",
    20,
    16,
    "1611z 14 Jan"
  ],
  "1724523419": [
    "W6YX",
    "3550.0",
    "KO6BPT",
    32,
    13,
    "0532z 12 Jan"
  ],
  "1724523339": [
    "K6FOD",
    "3550.0",
    "KO6BPT",
    26,
    13,
    "0532z 12 Jan"
  ],
  "1724515776": [
    "N9CO",
    "7045.0",
    "KO6BP",
    7,
    17,
    "0447z 12 Jan"
  ],
  "1682269657": [
    "S53A",
    "7026.2",
    "KO6BXE",
    37,
    18,
    "1817z 11 Nov"
  ],
  "1668887165": [
    "S53A",
    "7015.0",
    "KO6BHN",
    24,
    24,
    "0422z 19 Oct"
  ],
  "1654185288": [
    "DJ9IE",
    "7002.7",
    "KO6BHN",
    21,
    15,
    "0507z 21 Sep"
  ],
  "1654185146": [
    "W6YX",
    "7002.7",
    "KO6BHN",
    20,
    15,
    "0505z 21 Sep"
  ],
  "1654185142": [
    "DL8LAS",
    "7002.7",
    "KO6BHN",
    9,
    15,
    "0505z 21 Sep"
  ],
  "1654185138": [
    "DM5GG",
    "7002.7",
    "KO6BHN",
    15,
    15,
    "0505z 21 Sep"
  ],
  "1650895642": [
    "N6TV",
    "3577.5",
    "KO6BD",
    33,
    22,
    "0437z 13 Sep"
  ]
}
