{
  "1650259860": [
    "AC0C-1",
    "14058.1",
    "KD0FNR",
    3,
    30,
    "0329z 11 Sep"
  ],
  "1650259801": [
    "VE6AO",
    "14058.1",
    "KD0FNR",
    4,
    30,
    "0329z 11 Sep"
  ],
  "1650259764": [
    "VE6WZ",
    "14058.2",
    "KD0FNR",
    13,
    30,
    "0328z 11 Sep"
  ],
  "1650259759": [
    "VE6JY",
    "14058.1",
    "KD0FNR",
    17,
    30,
    "0328z 11 Sep"
  ],
  "1650259750": [
    "W6BB",
    "14058.1",
    "KD0FNR",
    15,
    30,
    "0328z 11 Sep"
  ],
  "1650259717": [
    "VE6WZ",
    "14057.6",
    "KD0FNR",
    6,
    30,
    "0328z 11 Sep"
  ],
  "1650259535": [
    "VE6JY",
    "14057.6",
    "KD0FNR",
    12,
    30,
    "0327z 11 Sep"
  ],
  "1650259516": [
    "W6BB",
    "14057.6",
    "KD0FNR",
    15,
    30,
    "0327z 11 Sep"
  ],
  "1650253965": [
    "ND7K",
    "14057.5",
    "KD0FNR",
    14,
    20,
    "0227z 11 Sep"
  ],
  "1650253961": [
    "VE6JY",
    "14057.5",
    "KD0FNR",
    8,
    20,
    "0227z 11 Sep"
  ],
  "1650253955": [
    "AC0C-1",
    "14057.5",
    "KD0FNR",
    8,
    20,
    "0226z 11 Sep"
  ],
  "1650253895": [
    "AC0C-1",
    "14058.1",
    "KD0FNR",
    6,
    20,
    "0225z 11 Sep"
  ],
  "1650253888": [
    "W6BB",
    "14058.1",
    "KD0FNR",
    13,
    20,
    "0225z 11 Sep"
  ],
  "1650253884": [
    "KO7SS",
    "14058.1",
    "KD0FNR",
    4,
    20,
    "0225z 11 Sep"
  ],
  "1650253822": [
    "K5EM",
    "14058.1",
    "KD0FNR",
    6,
    20,
    "0225z 11 Sep"
  ],
  "1650253728": [
    "NG7M",
    "14058.1",
    "KD0FNR",
    8,
    20,
    "0224z 11 Sep"
  ],
  "1650253727": [
    "N7TUG",
    "14058.3",
    "KD0FNR",
    0,
    20,
    "0224z 11 Sep"
  ],
  "1650253726": [
    "VE6JY",
    "14058.1",
    "KD0FNR",
    10,
    20,
    "0224z 11 Sep"
  ],
  "1650253714": [
    "ND7K",
    "14058.1",
    "KD0FNR",
    9,
    20,
    "0224z 11 Sep"
  ],
  "1650252829": [
    "KO7SS",
    "14058.1",
    "KD0FNR",
    5,
    18,
    "0215z 11 Sep"
  ],
  "1650252761": [
    "K5EM",
    "14058.1",
    "KD0FNR",
    6,
    17,
    "0215z 11 Sep"
  ],
  "1650252657": [
    "W6BB",
    "14058.1",
    "KD0FNR",
    13,
    22,
    "0213z 11 Sep"
  ],
  "1650252656": [
    "N7TUG",
    "14058.3",
    "KD0FNR",
    4,
    23,
    "0213z 11 Sep"
  ],
  "1650252654": [
    "ND7K",
    "14058.1",
    "KD0FNR",
    10,
    22,
    "0213z 11 Sep"
  ],
  "1650252651": [
    "VE6JY",
    "14058.1",
    "KD0FNR",
    9,
    22,
    "0213z 11 Sep"
  ],
  "1650252649": [
    "NG7M",
    "14058.1",
    "KD0FNR",
    11,
    22,
    "0213z 11 Sep"
  ],
  "1650252574": [
    "VE6WZ",
    "14058.1",
    "KD0FNR",
    2,
    22,
    "0212z 11 Sep"
  ],
  "1650252213": [
    "WF7U",
    "14058.1",
    "KD0FNR",
    3,
    22,
    "0209z 11 Sep"
  ],
  "1650251794": [
    "K5EM",
    "14058.1",
    "KD0FNR",
    9,
    21,
    "0205z 11 Sep"
  ],
  "1650251742": [
    "KO7SS",
    "14058.1",
    "KD0FNR",
    5,
    22,
    "0205z 11 Sep"
  ],
  "1650251610": [
    "ND7K",
    "14058.1",
    "KD0FNR",
    17,
    21,
    "0204z 11 Sep"
  ],
  "1650251514": [
    "VE6JY",
    "14058.1",
    "KD0FNR",
    15,
    21,
    "0203z 11 Sep"
  ],
  "1650251504": [
    "N7TUG",
    "14058.3",
    "KD0FNR",
    8,
    21,
    "0203z 11 Sep"
  ],
  "1650251474": [
    "NG7M",
    "14058.1",
    "KD0FNR",
    11,
    22,
    "0203z 11 Sep"
  ],
  "1650251470": [
    "W6BB",
    "14058.1",
    "KD0FNR",
    13,
    21,
    "0203z 11 Sep"
  ],
  "1650251318": [
    "KO7SS",
    "14057.5",
    "KD0FNR",
    6,
    22,
    "0201z 11 Sep"
  ],
  "1650251186": [
    "VE6WZ",
    "14057.6",
    "KD0FNR",
    4,
    22,
    "0200z 11 Sep"
  ],
  "1650251147": [
    "ND7K",
    "14057.5",
    "KD0FNR",
    14,
    22,
    "0200z 11 Sep"
  ],
  "1650251144": [
    "VE6JY",
    "14057.5",
    "KD0FNR",
    10,
    22,
    "0200z 11 Sep"
  ],
  "1650251142": [
    "W6BB",
    "14057.5",
    "KD0FNR",
    14,
    21,
    "0200z 11 Sep"
  ],
  "1650251141": [
    "NG7M",
    "14057.5",
    "KD0FNR",
    14,
    22,
    "0200z 11 Sep"
  ],
  "1650063346": [
    "KO7SS",
    "14057.5",
    "KD0FNR",
    6,
    21,
    "1526z 10 Sep"
  ],
  "1650063320": [
    "K7MJG",
    "14057.5",
    "KD0FNR",
    5,
    22,
    "1526z 10 Sep"
  ],
  "1650063316": [
    "VE6JY",
    "14057.5",
    "KD0FNR",
    9,
    22,
    "1526z 10 Sep"
  ],
  "1650063118": [
    "W6BB",
    "14057.5",
    "KD0FNR",
    13,
    21,
    "1526z 10 Sep"
  ],
  "1650063117": [
    "VE6WZ",
    "14057.6",
    "KD0FNR",
    9,
    22,
    "1526z 10 Sep"
  ],
  "1650050793": [
    "KO7SS",
    "14057.5",
    "KD0FNR",
    7,
    21,
    "1455z 10 Sep"
  ],
  "1650050791": [
    "VE6WZ",
    "14057.6",
    "KD0FNR",
    6,
    22,
    "1455z 10 Sep"
  ],
  "1650050591": [
    "VE6JY",
    "14057.5",
    "KD0FNR",
    6,
    22,
    "1454z 10 Sep"
  ],
  "1650050557": [
    "W6BB",
    "14057.5",
    "KD0FNR",
    14,
    21,
    "1454z 10 Sep"
  ],
  "1650046951": [
    "KO7SS",
    "14058.1",
    "KD0FNR",
    10,
    21,
    "1441z 10 Sep"
  ],
  "1650046409": [
    "W6BB",
    "14058.1",
    "KD0FNR",
    13,
    21,
    "1439z 10 Sep"
  ],
  "1650046148": [
    "K7MJG",
    "14058.1",
    "KD0FNR",
    5,
    22,
    "1438z 10 Sep"
  ],
  "1650046122": [
    "VE6AO",
    "14058.1",
    "KD0FNR",
    5,
    22,
    "1438z 10 Sep"
  ],
  "1650046032": [
    "VE6JY",
    "14058.1",
    "KD0FNR",
    4,
    22,
    "1438z 10 Sep"
  ],
  "1650044257": [
    "VE6AO",
    "14057.5",
    "KD0FNR",
    4,
    21,
    "1431z 10 Sep"
  ],
  "1650044069": [
    "W6BB",
    "14057.5",
    "KD0FNR",
    13,
    21,
    "1430z 10 Sep"
  ],
  "1650043991": [
    "VE6WZ",
    "14058.1",
    "KD0FNR",
    4,
    22,
    "1430z 10 Sep"
  ],
  "1650040606": [
    "VE6AO",
    "14058.1",
    "KD0FNR",
    8,
    21,
    "1420z 10 Sep"
  ],
  "1650040114": [
    "VE6WZ",
    "14058.2",
    "KD0FNR",
    6,
    21,
    "1419z 10 Sep"
  ],
  "1650038978": [
    "VE6JY",
    "14057.6",
    "KD0FNR",
    6,
    22,
    "1415z 10 Sep"
  ],
  "1650012004": [
    "W6BB",
    "14057.5",
    "KD0FNR",
    14,
    21,
    "1231z 10 Sep"
  ],
  "1650010458": [
    "W6BB",
    "14058.1",
    "KD0FNR",
    14,
    22,
    "1225z 10 Sep"
  ],
  "1650009401": [
    "W6BB",
    "14057.5",
    "KD0FNR",
    14,
    22,
    "1220z 10 Sep"
  ],
  "1650007561": [
    "W6BB",
    "14058.1",
    "KD0FNR",
    14,
    21,
    "1212z 10 Sep"
  ],
  "1650007085": [
    "W6BB",
    "14057.5",
    "KD0FNR",
    14,
    17,
    "1210z 10 Sep"
  ],
  "1650005024": [
    "W6BB",
    "14057.5",
    "KD0FNR",
    14,
    21,
    "1200z 10 Sep"
  ],
  "1650004177": [
    "W6BB",
    "14058.1",
    "KD0FNR",
    14,
    21,
    "1155z 10 Sep"
  ],
  "1650002321": [
    "W6BB",
    "14057.6",
    "KD0FNR",
    14,
    22,
    "1147z 10 Sep"
  ],
  "1649892311": [
    "W6BB",
    "14057.5",
    "KD0FNR",
    12,
    21,
    "0400z 10 Sep"
  ],
  "1649888505": [
    "AC0C-1",
    "14058.1",
    "KD0FNR",
    3,
    22,
    "0357z 10 Sep"
  ],
  "1649886804": [
    "W6BB",
    "14058.1",
    "KD0FNR",
    12,
    21,
    "0355z 10 Sep"
  ],
  "1649882958": [
    "AC0C-1",
    "14057.5",
    "KD0FNR",
    4,
    23,
    "0351z 10 Sep"
  ],
  "1649882175": [
    "W6BB",
    "14057.5",
    "KD0FNR",
    13,
    22,
    "0350z 10 Sep"
  ],
  "1649878590": [
    "AC0C-1",
    "14057.5",
    "KD0FNR",
    4,
    22,
    "0346z 10 Sep"
  ],
  "1649877269": [
    "KL7RA",
    "14057.5",
    "KD0FNR",
    5,
    21,
    "0345z 10 Sep"
  ],
  "1649872368": [
    "W6BB",
    "14057.5",
    "KD0FNR",
    12,
    21,
    "0340z 10 Sep"
  ],
  "1649871530": [
    "AC0C-1",
    "14057.5",
    "KD0FNR",
    3,
    22,
    "0340z 10 Sep"
  ],
  "1649869403": [
    "KL7RA",
    "14057.5",
    "KD0FNR",
    5,
    21,
    "0338z 10 Sep"
  ],
  "1649866422": [
    "AC0C-1",
    "14057.5",
    "KD0FNR",
    3,
    22,
    "0335z 10 Sep"
  ],
  "1649861484": [
    "W6BB",
    "14057.5",
    "KD0FNR",
    13,
    21,
    "0330z 10 Sep"
  ],
  "1649856386": [
    "AC0C-1",
    "14057.5",
    "KD0FNR",
    3,
    22,
    "0324z 10 Sep"
  ],
  "1649853182": [
    "KL7RA",
    "14057.5",
    "KD0FNR",
    4,
    22,
    "0321z 10 Sep"
  ],
  "1649852710": [
    "W6BB",
    "14057.5",
    "KD0FNR",
    13,
    22,
    "0320z 10 Sep"
  ],
  "1649846334": [
    "VE6JY",
    "14057.5",
    "KD0FNR",
    10,
    21,
    "0312z 10 Sep"
  ],
  "1649845510": [
    "KL7RA",
    "14057.5",
    "KD0FNR",
    7,
    22,
    "0311z 10 Sep"
  ],
  "1649844910": [
    "W6BB",
    "14057.5",
    "KD0FNR",
    12,
    21,
    "0310z 10 Sep"
  ],
  "1649837644": [
    "KL7RA",
    "14057.5",
    "KD0FNR",
    5,
    22,
    "0301z 10 Sep"
  ],
  "1649837071": [
    "W6BB",
    "14057.5",
    "KD0FNR",
    12,
    21,
    "0300z 10 Sep"
  ],
  "1649835286": [
    "VE6JY",
    "14058.1",
    "KD0FNR",
    13,
    21,
    "0258z 10 Sep"
  ],
  "1649835041": [
    "W6BB",
    "14058.1",
    "KD0FNR",
    12,
    21,
    "0258z 10 Sep"
  ],
  "1649830123": [
    "VE6JY",
    "14057.5",
    "KD0FNR",
    8,
    22,
    "0252z 10 Sep"
  ],
  "1649828892": [
    "KL7RA",
    "14057.5",
    "KD0FNR",
    7,
    22,
    "0251z 10 Sep"
  ],
  "1649823015": [
    "VE6JY",
    "14058.1",
    "KD0FNR",
    6,
    32,
    "0245z 10 Sep"
  ],
  "1649821795": [
    "W6BB",
    "14058.1",
    "KD0FNR",
    12,
    32,
    "0244z 10 Sep"
  ],
  "1649821711": [
    "VE6WZ",
    "14058.2",
    "KD0FNR",
    20,
    32,
    "0244z 10 Sep"
  ],
  "1649818786": [
    "KO7SS",
    "14057.5",
    "KD0FNR",
    5,
    29,
    "0241z 10 Sep"
  ],
  "1649713736": [
    "VE6JY",
    "14058.1",
    "KD0FNR",
    8,
    17,
    "0123z 10 Sep"
  ],
  "1649713646": [
    "KO7SS",
    "14058.1",
    "KD0FNR",
    13,
    17,
    "0123z 10 Sep"
  ],
  "1649713567": [
    "VE6WZ",
    "14058.2",
    "KD0FNR",
    13,
    17,
    "0123z 10 Sep"
  ]
}
