{
  "1879621254": [
    "NG7M",
    "14057.3",
    "KD0FNR",
    10,
    19,
    "1750z 15 Sep"
  ],
  "1879621242": [
    "VE6WZ",
    "14057.2",
    "KD0FNR",
    6,
    19,
    "1750z 15 Sep"
  ],
  "1879621236": [
    "W8WWV",
    "14057.2",
    "KD0FNN",
    8,
    19,
    "1750z 15 Sep"
  ],
  "1879621228": [
    "K7CO",
    "14057.3",
    "KD0FNR",
    7,
    19,
    "1750z 15 Sep"
  ],
  "1879621227": [
    "KA7OEI",
    "14057.3",
    "KD0FNR",
    29,
    18,
    "1750z 15 Sep"
  ],
  "1879621092": [
    "W6YX",
    "14057.3",
    "KD0FNR",
    13,
    19,
    "1749z 15 Sep"
  ],
  "1879621060": [
    "K3PA-1",
    "14057.3",
    "KD0FNR",
    25,
    18,
    "1749z 15 Sep"
  ],
  "1879621050": [
    "ND7K",
    "14057.3",
    "KD0FNR",
    19,
    19,
    "1749z 15 Sep"
  ],
  "1879621046": [
    "AC0C-1",
    "14057.3",
    "KD0FNR",
    32,
    19,
    "1749z 15 Sep"
  ],
  "1879621041": [
    "N9CO",
    "14057.3",
    "KD0FNR",
    11,
    19,
    "1749z 15 Sep"
  ],
  "1879613932": [
    "VE6WZ",
    "14057.2",
    "KD0FNR",
    7,
    19,
    "1730z 15 Sep"
  ],
  "1879613113": [
    "W8WWV",
    "14057.2",
    "KD0FNR",
    9,
    19,
    "1729z 15 Sep"
  ],
  "1879613091": [
    "WS2C",
    "14057.3",
    "KD0FNR",
    9,
    19,
    "1729z 15 Sep"
  ],
  "1879612574": [
    "N9CO",
    "14057.2",
    "KD0FNR",
    9,
    19,
    "1727z 15 Sep"
  ],
  "1879612392": [
    "WE9V",
    "14057.2",
    "KD0FNR",
    9,
    19,
    "1727z 15 Sep"
  ],
  "1879612362": [
    "N6TV",
    "14057.3",
    "KD0FNR",
    14,
    19,
    "1727z 15 Sep"
  ],
  "1879612357": [
    "NG7M",
    "14057.3",
    "KD0FNR",
    11,
    19,
    "1727z 15 Sep"
  ],
  "1879612033": [
    "AC0C-1",
    "14057.3",
    "KD0FNR",
    29,
    19,
    "1726z 15 Sep"
  ],
  "1879610968": [
    "ND7K",
    "14057.3",
    "KD0FNR",
    23,
    20,
    "1723z 15 Sep"
  ],
  "1879610965": [
    "W6YX",
    "14057.3",
    "KD0FNR",
    28,
    21,
    "1723z 15 Sep"
  ],
  "1879610946": [
    "K3PA-1",
    "14057.3",
    "KD0FNR",
    20,
    21,
    "1723z 15 Sep"
  ],
  "1879610944": [
    "VE6JY",
    "14057.3",
    "KD0FNR",
    30,
    21,
    "1723z 15 Sep"
  ],
  "1879609987": [
    "VE6WZ",
    "14057.2",
    "KD0FNR",
    15,
    20,
    "1720z 15 Sep"
  ],
  "1879605622": [
    "NG7M",
    "14057.3",
    "KD0FNR",
    12,
    20,
    "1708z 15 Sep"
  ],
  "1879605577": [
    "ND7K",
    "14057.3",
    "KD0FNR",
    18,
    20,
    "1708z 15 Sep"
  ],
  "1879605478": [
    "K3PA-1",
    "14057.3",
    "KD0FNR",
    24,
    21,
    "1707z 15 Sep"
  ],
  "1879605457": [
    "N6TV",
    "14057.3",
    "KD0FNR",
    13,
    21,
    "1707z 15 Sep"
  ],
  "1879605447": [
    "AC0C-1",
    "14057.3",
    "KD0FNR",
    20,
    21,
    "1707z 15 Sep"
  ],
  "1879150854": [
    "KO7SS",
    "14057.3",
    "KD0FNR",
    8,
    19,
    "1424z 14 Sep"
  ],
  "1879150839": [
    "K3PA-1",
    "14057.3",
    "KD0FNR",
    34,
    19,
    "1424z 14 Sep"
  ],
  "1879150823": [
    "N6TV",
    "14057.3",
    "KD0FNR",
    15,
    19,
    "1424z 14 Sep"
  ],
  "1879150802": [
    "W8WWV",
    "14057.2",
    "KD0FNR",
    13,
    18,
    "1424z 14 Sep"
  ],
  "1879148951": [
    "AC0C-1",
    "14057.3",
    "KD0FNR",
    31,
    19,
    "1421z 14 Sep"
  ],
  "1879148940": [
    "VE3EID",
    "14057.3",
    "KD0FNR",
    21,
    19,
    "1421z 14 Sep"
  ],
  "1879148928": [
    "VE6JY",
    "14057.3",
    "KD0FNR",
    25,
    19,
    "1421z 14 Sep"
  ],
  "1879148917": [
    "N9CO",
    "14057.3",
    "KD0FNR",
    22,
    19,
    "1421z 14 Sep"
  ],
  "1879148740": [
    "VE6AO",
    "14057.3",
    "KD0FNR",
    14,
    19,
    "1421z 14 Sep"
  ],
  "1879148697": [
    "VE6WZ",
    "14057.2",
    "KD0FNR",
    13,
    19,
    "1421z 14 Sep"
  ],
  "1879148695": [
    "ND7K",
    "14057.3",
    "KD0FNR",
    29,
    19,
    "1421z 14 Sep"
  ],
  "1879146226": [
    "K7MJG",
    "14057.3",
    "KD0FNR",
    5,
    19,
    "1417z 14 Sep"
  ],
  "1879146196": [
    "WS2C",
    "14057.3",
    "KD0FNR",
    7,
    19,
    "1417z 14 Sep"
  ],
  "1879145388": [
    "WX7V/5",
    "14057.3",
    "KD0FNR",
    12,
    19,
    "1416z 14 Sep"
  ],
  "1879144727": [
    "N9CO",
    "14057.3",
    "KD0FNR",
    27,
    19,
    "1415z 14 Sep"
  ],
  "1879143726": [
    "K9LC",
    "14057.3",
    "KD0FNR",
    26,
    19,
    "1414z 14 Sep"
  ],
  "1879143130": [
    "W6YX",
    "14057.3",
    "KD0FNR",
    19,
    19,
    "1413z 14 Sep"
  ],
  "1879143120": [
    "WV4P",
    "14057.3",
    "KD0FNR",
    6,
    19,
    "1413z 14 Sep"
  ],
  "1879143111": [
    "K3PA-1",
    "14057.3",
    "KD0FNR",
    29,
    19,
    "1413z 14 Sep"
  ],
  "1879143101": [
    "TI7W",
    "14057.3",
    "KD0FNR",
    24,
    19,
    "1413z 14 Sep"
  ],
  "1879141747": [
    "ND7K",
    "14057.3",
    "KD0FNR",
    29,
    21,
    "1411z 14 Sep"
  ],
  "1879141736": [
    "AC0C-1",
    "14057.3",
    "KD0FNR",
    23,
    21,
    "1411z 14 Sep"
  ],
  "1879141735": [
    "W8WWV",
    "14057.2",
    "KD0FNR",
    10,
    20,
    "1411z 14 Sep"
  ],
  "1879141466": [
    "VE6AO",
    "14057.3",
    "KD0FNR",
    16,
    21,
    "1411z 14 Sep"
  ],
  "1879141347": [
    "K5TR",
    "14057.3",
    "KD0FNR",
    4,
    21,
    "1410z 14 Sep"
  ],
  "1879141139": [
    "KO7SS",
    "14057.3",
    "KD0FNR",
    7,
    20,
    "1410z 14 Sep"
  ],
  "1879141095": [
    "VE6JY",
    "14057.3",
    "KD0FNR",
    23,
    21,
    "1410z 14 Sep"
  ],
  "1879140704": [
    "N6TV",
    "14057.3",
    "KD0FNR",
    7,
    20,
    "1410z 14 Sep"
  ],
  "1879140688": [
    "VE6WZ",
    "14057.2",
    "KD0FNR",
    17,
    21,
    "1410z 14 Sep"
  ],
  "1879140671": [
    "VE3EID",
    "14057.3",
    "KD0FNR",
    26,
    20,
    "1410z 14 Sep"
  ],
  "1879138321": [
    "WS2C",
    "14057.3",
    "KD0FNR",
    4,
    20,
    "1406z 14 Sep"
  ],
  "1879137657": [
    "WV4P",
    "14057.3",
    "KD0FNR",
    6,
    21,
    "1405z 14 Sep"
  ],
  "1879136980": [
    "ZL4YL",
    "14057.3",
    "KD0FNR",
    7,
    21,
    "1404z 14 Sep"
  ],
  "1879136200": [
    "K7MJG",
    "14057.3",
    "KD0FNR",
    5,
    21,
    "1403z 14 Sep"
  ],
  "1879135426": [
    "TI7W",
    "14057.3",
    "KD0FNR",
    13,
    21,
    "1402z 14 Sep"
  ],
  "1879135413": [
    "K3PA-1",
    "14057.3",
    "KD0FNR",
    25,
    20,
    "1402z 14 Sep"
  ],
  "1879134828": [
    "W6YX",
    "14057.3",
    "KD0FNR",
    23,
    19,
    "1401z 14 Sep"
  ],
  "1879134592": [
    "ND7K",
    "14057.3",
    "KD0FNR",
    26,
    19,
    "1401z 14 Sep"
  ],
  "1879134582": [
    "W8WWV",
    "14057.3",
    "KD0FNR",
    12,
    19,
    "1401z 14 Sep"
  ],
  "1879134343": [
    "K5TR",
    "14057.3",
    "KD0FNR",
    7,
    19,
    "1400z 14 Sep"
  ],
  "1879134329": [
    "WX7V/5",
    "14057.3",
    "KD0FNR",
    7,
    19,
    "1400z 14 Sep"
  ],
  "1879134172": [
    "VE6AO",
    "14057.3",
    "KD0FNR",
    17,
    19,
    "1400z 14 Sep"
  ],
  "1879134164": [
    "KO7SS",
    "14057.3",
    "KD0FNR",
    9,
    19,
    "1400z 14 Sep"
  ],
  "1879134158": [
    "WE9V",
    "14057.3",
    "KD0FNR",
    6,
    19,
    "1400z 14 Sep"
  ],
  "1879134126": [
    "VE6JY",
    "14057.3",
    "KD0FNR",
    29,
    19,
    "1400z 14 Sep"
  ],
  "1879132550": [
    "W1NT-2",
    "14057.3",
    "KD0FNR",
    17,
    21,
    "1357z 14 Sep"
  ],
  "1879132545": [
    "VE3EID",
    "14057.3",
    "KD0FNR",
    21,
    20,
    "1357z 14 Sep"
  ],
  "1879132530": [
    "N6TV",
    "14057.3",
    "KD0FNR",
    11,
    20,
    "1357z 14 Sep"
  ],
  "1879132483": [
    "K9LC",
    "14057.3",
    "KD0FNR",
    7,
    21,
    "1357z 14 Sep"
  ],
  "1879132474": [
    "K3PA-1",
    "14057.3",
    "KD0FNR",
    33,
    21,
    "1357z 14 Sep"
  ],
  "1879132247": [
    "ND7K",
    "14057.3",
    "KD0FNR",
    30,
    21,
    "1357z 14 Sep"
  ],
  "1879132245": [
    "AC0C-1",
    "14057.3",
    "KD0FNR",
    24,
    21,
    "1357z 14 Sep"
  ],
  "1879132208": [
    "VE6WZ",
    "14057.2",
    "KD0FNR",
    19,
    20,
    "1357z 14 Sep"
  ],
  "1879132165": [
    "N6TV",
    "14057.3",
    "KD0FNR",
    11,
    21,
    "1357z 14 Sep"
  ],
  "1879128265": [
    "KO7SS",
    "14057.4",
    "KD0FNR",
    10,
    21,
    "1350z 14 Sep"
  ],
  "1879128245": [
    "VE7CC",
    "14057.4",
    "KD0FNR",
    12,
    21,
    "1350z 14 Sep"
  ],
  "1879127929": [
    "VE6JY",
    "14057.4",
    "KD0FNR",
    24,
    21,
    "1349z 14 Sep"
  ],
  "1879127556": [
    "TI7W",
    "14057.4",
    "KD0FNR",
    11,
    17,
    "1349z 14 Sep"
  ],
  "1879126300": [
    "W8WWV",
    "14057.4",
    "KD0FNR",
    10,
    20,
    "1347z 14 Sep"
  ],
  "1879126298": [
    "WC2L",
    "14057.4",
    "KD0FNR",
    5,
    20,
    "1347z 14 Sep"
  ],
  "1879125000": [
    "ND7K",
    "14057.4",
    "KD0FNR",
    12,
    21,
    "1345z 14 Sep"
  ],
  "1879123217": [
    "VE3EID",
    "14057.4",
    "KD0FNR",
    12,
    21,
    "1342z 14 Sep"
  ],
  "1879123129": [
    "NT6Q",
    "14057.5",
    "KD0FNR",
    18,
    20,
    "1342z 14 Sep"
  ],
  "1879123123": [
    "K9LC",
    "14057.4",
    "KD0FNR",
    5,
    21,
    "1342z 14 Sep"
  ],
  "1879123095": [
    "WX7V/5",
    "14057.5",
    "KD0FNR",
    5,
    20,
    "1342z 14 Sep"
  ],
  "1879123079": [
    "W1NT-2",
    "14057.5",
    "KD0FNR",
    6,
    21,
    "1342z 14 Sep"
  ],
  "1879122947": [
    "AC0C-1",
    "14057.4",
    "KD0FNR",
    23,
    21,
    "1341z 14 Sep"
  ],
  "1879122937": [
    "K5TR",
    "14057.5",
    "KD0FNR",
    8,
    21,
    "1341z 14 Sep"
  ],
  "1879122916": [
    "K3PA-1",
    "14057.4",
    "KD0FNR",
    22,
    21,
    "1341z 14 Sep"
  ],
  "1879122909": [
    "W6YX",
    "14057.4",
    "KD0FNR",
    20,
    21,
    "1341z 14 Sep"
  ],
  "1879122893": [
    "N9CO",
    "14057.4",
    "KD0FNR",
    7,
    20,
    "1341z 14 Sep"
  ],
  "1878728277": [
    "WC2L",
    "14057.4",
    "KD0FNR",
    5,
    19,
    "1255z 13 Sep"
  ]
,
  "1848235773": [
    "W6YX",
    "7062.0",
    "KO6BTM",
    25,
    16,
    "1647z 07 Jul"
  ],
  "1848233335": [
    "W6YX",
    "7062.0",
    "KO6BTM",
    25,
    16,
    "1640z 07 Jul"
  ],
  "1782833996": [
    "W3RGA",
    "7069.1",
    "KO6BLZ",
    12,
    45,
    "0148z 18 Mar"
  ],
  "1782833969": [
    "K9LC",
    "7069.1",
    "KO6BLZ",
    15,
    45,
    "0148z 18 Mar"
  ],
  "1782833966": [
    "WZ7I",
    "7069.1",
    "KO6BLZ",
    13,
    45,
    "0148z 18 Mar"
  ],
  "1782833921": [
    "KO7SS",
    "7069.1",
    "KO6BLZ",
    22,
    45,
    "0147z 18 Mar"
  ],
  "1782833890": [
    "WE9V",
    "7069.1",
    "KO6BLZ",
    16,
    45,
    "0147z 18 Mar"
  ],
  "1782833887": [
    "W6YX",
    "7069.1",
    "KO6BLZ",
    37,
    45,
    "0147z 18 Mar"
  ],
  "1782833885": [
    "WA7LNW",
    "7069.1",
    "KO6BLZ",
    35,
    45,
    "0147z 18 Mar"
  ],
  "1782833870": [
    "K6FOD",
    "7069.1",
    "KO6BLZ",
    19,
    45,
    "0147z 18 Mar"
  ],
  "1782833859": [
    "W6BB",
    "7069.1",
    "KO6BLZ",
    27,
    45,
    "0147z 18 Mar"
  ],
  "1782833851": [
    "NU6XB",
    "7069.1",
    "KO6BLZ",
    28,
    45,
    "0147z 18 Mar"
  ],
  "1782833849": [
    "NG7M",
    "7069.1",
    "KO6BLZ",
    20,
    45,
    "0147z 18 Mar"
  ],
  "1782524776": [
    "K9LC",
    "28090.0",
    "KO6BLZ",
    22,
    45,
    "1620z 17 Mar"
  ],
  "1781441497": [
    "WC2L",
    "7082.5",
    "KO6BLZ",
    11,
    45,
    "0521z 17 Mar"
  ],
  "1781440747": [
    "WV4P",
    "7082.6",
    "KO6BLZ",
    14,
    45,
    "0520z 17 Mar"
  ],
  "1781440221": [
    "K9LC",
    "7082.5",
    "KO6BLZ",
    21,
    45,
    "0520z 17 Mar"
  ],
  "1781439297": [
    "WA7LNW",
    "7082.5",
    "KO6BLZ",
    35,
    45,
    "0520z 17 Mar"
  ],
  "1781439213": [
    "KO7SS",
    "7082.5",
    "KO6BLZ",
    27,
    45,
    "0520z 17 Mar"
  ],
  "1781439187": [
    "WZ7I",
    "7082.6",
    "KO6BLZ",
    15,
    45,
    "0520z 17 Mar"
  ],
  "1781439091": [
    "WE9V",
    "7082.5",
    "KO6BLZ",
    22,
    45,
    "0519z 17 Mar"
  ],
  "1781438972": [
    "VE7CC",
    "7082.6",
    "KO6BLZ",
    18,
    45,
    "0519z 17 Mar"
  ],
  "1781306329": [
    "WV4P",
    "7063.0",
    "KO6BLZ",
    12,
    45,
    "0350z 17 Mar"
  ],
  "1781305739": [
    "W3RGA",
    "7063.0",
    "KO6BLZ",
    13,
    45,
    "0350z 17 Mar"
  ],
  "1781305664": [
    "WE9V",
    "7063.0",
    "KO6BLZ",
    19,
    45,
    "0349z 17 Mar"
  ],
  "1781305568": [
    "WA7LNW",
    "7063.0",
    "KO6BLZ",
    39,
    45,
    "0349z 17 Mar"
  ],
  "1781305521": [
    "WZ7I",
    "7063.0",
    "KO6BLZ",
    14,
    45,
    "0349z 17 Mar"
  ],
  "1781305464": [
    "W6YX",
    "7063.0",
    "KO6BLZ",
    35,
    45,
    "0349z 17 Mar"
  ],
  "1781305442": [
    "K9LC",
    "7063.0",
    "KO6BLZ",
    18,
    45,
    "0349z 17 Mar"
  ],
  "1781305440": [
    "KO7SS",
    "7063.0",
    "KO6BLZ",
    25,
    45,
    "0349z 17 Mar"
  ],
  "1781305412": [
    "NU6XB",
    "7063.0",
    "KO6BLZ",
    24,
    45,
    "0349z 17 Mar"
  ],
  "1781305409": [
    "K6FOD",
    "7063.0",
    "KO6BLZ",
    23,
    45,
    "0349z 17 Mar"
  ],
  "1781305367": [
    "W6BB",
    "7063.0",
    "KO6BLZ",
    31,
    45,
    "0349z 17 Mar"
  ],
  "1781282634": [
    "W3RGA",
    "14091.6",
    "KO6BLZ",
    12,
    45,
    "0332z 17 Mar"
  ],
  "1781282378": [
    "KO7SS",
    "14091.6",
    "KO6BLZ",
    30,
    45,
    "0331z 17 Mar"
  ],
  "1781282328": [
    "WC2L",
    "14091.6",
    "KO6BLZ",
    20,
    45,
    "0331z 17 Mar"
  ],
  "1781278832": [
    "WE9V",
    "7086.5",
    "KO6BLZ",
    17,
    45,
    "0329z 17 Mar"
  ],
  "1781278536": [
    "KO7SS",
    "7086.6",
    "KO6BLZ",
    23,
    45,
    "0328z 17 Mar"
  ],
  "1781278496": [
    "W6YX",
    "7086.6",
    "KO6BLZ",
    28,
    45,
    "0328z 17 Mar"
  ],
  "1781278464": [
    "AC0C-1",
    "7086.6",
    "KO6BLZ",
    16,
    45,
    "0328z 17 Mar"
  ],
  "1781278241": [
    "NU6XB",
    "7086.6",
    "KO6BLZ",
    25,
    45,
    "0328z 17 Mar"
  ],
  "1781278201": [
    "K9LC",
    "7086.6",
    "KO6BLZ",
    19,
    45,
    "0328z 17 Mar"
  ],
  "1781278189": [
    "WA7LNW",
    "7086.6",
    "KO6BLZ",
    41,
    45,
    "0328z 17 Mar"
  ],
  "1781278155": [
    "N6TV",
    "7086.6",
    "KO6BLZ",
    38,
    45,
    "0328z 17 Mar"
  ],
  "1781278153": [
    "KE3BK",
    "7086.6",
    "KO6BLZ",
    45,
    45,
    "0328z 17 Mar"
  ],
  "1781278146": [
    "K6FOD",
    "7086.6",
    "KO6BLZ",
    29,
    45,
    "0328z 17 Mar"
  ],
  "1781278104": [
    "W6BB",
    "7086.6",
    "KO6BLZ",
    29,
    45,
    "0328z 17 Mar"
  ],
  "1781278089": [
    "VE7CC",
    "7086.6",
    "KO6BLZ",
    20,
    45,
    "0328z 17 Mar"
  ],
  "1767188912": [
    "W3RGA",
    "7101.7",
    "KO6BLZ",
    17,
    45,
    "0329z 25 Feb"
  ],
  "1767188890": [
    "N6TV",
    "7101.7",
    "KO6BLZ",
    14,
    45,
    "0329z 25 Feb"
  ],
  "1767188883": [
    "WZ7I",
    "7101.7",
    "KO6BLZ",
    21,
    45,
    "0329z 25 Feb"
  ],
  "1767188872": [
    "AC0C-1",
    "7101.7",
    "KO6BLZ",
    21,
    45,
    "0329z 25 Feb"
  ],
  "1767188759": [
    "KO7SS",
    "7101.7",
    "KO6BLZ",
    21,
    45,
    "0329z 25 Feb"
  ],
  "1767188701": [
    "WA7LNW",
    "7101.7",
    "KO6BLZ",
    37,
    45,
    "0329z 25 Feb"
  ],
  "1767188684": [
    "NG7M",
    "7101.7",
    "KO6BLZ",
    32,
    45,
    "0329z 25 Feb"
  ],
  "1767158617": [
    "W3RGA",
    "7084.1",
    "KO6BLZ",
    12,
    45,
    "0216z 25 Feb"
  ],
  "1767158405": [
    "K9LC",
    "7084.1",
    "KO6BLZ",
    14,
    45,
    "0216z 25 Feb"
  ],
  "1767158242": [
    "WZ7I",
    "7084.2",
    "KO6BLZ",
    15,
    45,
    "0216z 25 Feb"
  ],
  "1767158164": [
    "WA7LNW",
    "7084.1",
    "KO6BLZ",
    35,
    45,
    "0216z 25 Feb"
  ],
  "1767158152": [
    "WE9V",
    "7084.1",
    "KO6BLZ",
    20,
    45,
    "0216z 25 Feb"
  ],
  "1767158013": [
    "AC0C-1",
    "7084.1",
    "KO6BLZ",
    22,
    45,
    "0215z 25 Feb"
  ],
  "1767157953": [
    "KO7SS",
    "7084.1",
    "KO6BLZ",
    25,
    45,
    "0215z 25 Feb"
  ],
  "1767157934": [
    "N6TV",
    "7084.1",
    "KO6BLZ",
    33,
    45,
    "0215z 25 Feb"
  ],
  "1767157922": [
    "W6YX",
    "7084.1",
    "KO6BLZ",
    32,
    45,
    "0215z 25 Feb"
  ],
  "1767157894": [
    "NU6XB",
    "7084.1",
    "KO6BLZ",
    23,
    45,
    "0215z 25 Feb"
  ],
  "1767157883": [
    "W6BB",
    "7084.1",
    "KO6BLZ",
    30,
    45,
    "0215z 25 Feb"
  ],
  "1767157874": [
    "NG7M",
    "7084.1",
    "KO6BLZ",
    24,
    45,
    "0215z 25 Feb"
  ],
  "1767157871": [
    "K6FOD",
    "7084.1",
    "KO6BLZ",
    20,
    45,
    "0215z 25 Feb"
  ],
  "1766829105": [
    "KO7SS",
    "21085.4",
    "KO6BLZ",
    14,
    45,
    "2045z 24 Feb"
  ],
  "1766828777": [
    "VE7CC",
    "21085.4",
    "KO6BLZ",
    20,
    45,
    "2045z 24 Feb"
  ],
  "1765893027": [
    "NG7M",
    "14070.0",
    "KO6BLZ",
    19,
    45,
    "2114z 23 Feb"
  ],
  "1765513663": [
    "NG7M",
    "7036.4",
    "KO6BPT",
    27,
    15,
    "0433z 23 Feb"
  ],
  "1765512201": [
    "NG7M",
    "7036.4",
    "KO6BPT",
    27,
    13,
    "0426z 23 Feb"
  ],
  "1765492892": [
    "ND7K",
    "7055.5",
    "KO6BPT",
    38,
    13,
    "0235z 23 Feb"
  ],
  "1762199006": [
    "WZ7I",
    "28060.3",
    "KO6BL",
    5,
    29,
    "1855z 18 Feb"
  ],
  "1761753675": [
    "WA7LNW",
    "14035.2",
    "KO6BLZ",
    40,
    26,
    "1716z 18 Feb"
  ],
  "1761635062": [
    "K7MJG",
    "14031.6",
    "KO6BLZ",
    3,
    30,
    "1651z 18 Feb"
  ],
  "1758469793": [
    "WA7LNW",
    "7029.0",
    "KO6BLZ",
    33,
    30,
    "0246z 18 Feb"
  ],
  "1754580679": [
    "VE6WZ",
    "7027.0",
    "KO6BLZ",
    28,
    26,
    "0821z 17 Feb"
  ],
  "1753581564": [
    "VE6JY",
    "7059.5",
    "KO6BLZ",
    49,
    29,
    "0305z 17 Feb"
  ],
  "1753527029": [
    "W6YX",
    "7063.1",
    "KO6BLZ",
    27,
    33,
    "0248z 17 Feb"
  ],
  "1753526799": [
    "WA7LNW",
    "7063.1",
    "KO6BLZ",
    34,
    33,
    "0248z 17 Feb"
  ],
  "1753205246": [
    "K7MJG",
    "14037.3",
    "KO6BLZ",
    3,
    26,
    "0115z 17 Feb"
  ],
  "1752836547": [
    "WA7LNW",
    "14041.8",
    "KO6BLZ",
    19,
    17,
    "2008z 16 Feb"
  ],
  "1750533148": [
    "W3RGA",
    "21095.5",
    "KO6BLZ",
    10,
    45,
    "2355z 11 Feb"
  ],
  "1750532860": [
    "AC0C-1",
    "21095.5",
    "KO6BLZ",
    16,
    45,
    "2355z 11 Feb"
  ],
  "1750532849": [
    "KH6LC",
    "21095.5",
    "KO6BLZ",
    12,
    45,
    "2355z 11 Feb"
  ],
  "1750532815": [
    "WZ7I",
    "21095.5",
    "KO6BLZ",
    15,
    45,
    "2355z 11 Feb"
  ],
  "1750532727": [
    "K9LC",
    "21095.5",
    "KO6BLZ",
    21,
    45,
    "2355z 11 Feb"
  ],
  "1750532588": [
    "VE7CC",
    "21095.5",
    "KO6BLZ",
    22,
    45,
    "2355z 11 Feb"
  ],
  "1750499519": [
    "WZ7I",
    "21082.6",
    "KO6BLZ",
    13,
    45,
    "2307z 11 Feb"
  ],
  "1750499419": [
    "K9LC",
    "21082.6",
    "KO6BLZ",
    16,
    45,
    "2307z 11 Feb"
  ],
  "1750499403": [
    "AC0C-1",
    "21082.6",
    "KO6BLZ",
    18,
    45,
    "2307z 11 Feb"
  ],
  "1750498869": [
    "KH6LC",
    "21082.6",
    "KO6BLZ",
    15,
    45,
    "2306z 11 Feb"
  ],
  "1750479166": [
    "WZ7I",
    "21130.4",
    "KO6BLZ",
    17,
    45,
    "2242z 11 Feb"
  ],
  "1750479105": [
    "KH6LC",
    "21130.5",
    "KO6BLZ",
    14,
    45,
    "2242z 11 Feb"
  ],
  "1750478916": [
    "K9LC",
    "21130.5",
    "KO6BLZ",
    17,
    45,
    "2241z 11 Feb"
  ],
  "1750478695": [
    "AC0C-1",
    "21130.4",
    "KO6BLZ",
    15,
    45,
    "2241z 11 Feb"
  ],
  "1750283722": [
    "K9LC",
    "21088.9",
    "KO6BLZ",
    10,
    45,
    "1924z 11 Feb"
  ],
  "1750283377": [
    "AC0C-1",
    "21088.9",
    "KO6BLZ",
    18,
    45,
    "1923z 11 Feb"
  ]
}
