{
  "1733914977": [
    "W1NT-6",
    "14057.5",
    "KD0FNR/6",
    5,
    16,
    "1248z 24 Jan"
  ],
  "1733914651": [
    "W1NT-2",
    "14057.5",
    "KD0FNR/6",
    5,
    16,
    "1247z 24 Jan"
  ],
  "1733914335": [
    "WA7LNW",
    "14057.5",
    "KD0FNR/6",
    18,
    16,
    "1246z 24 Jan"
  ],
  "1733914184": [
    "W6YX",
    "14057.5",
    "KD0FNR/6",
    23,
    16,
    "1245z 24 Jan"
  ],
  "1733898807": [
    "WA7LNW",
    "14057.4",
    "KD0FNR/6",
    8,
    16,
    "1156z 24 Jan"
  ],
  "1733898486": [
    "ND7K",
    "14057.4",
    "KD0FNR/6",
    13,
    16,
    "1155z 24 Jan"
  ],
  "1733898050": [
    "W6YX",
    "14057.4",
    "KD0FNR/6",
    23,
    17,
    "1154z 24 Jan"
  ],
  "1733895789": [
    "W8WWV",
    "14057.4",
    "KD0FNR/6",
    4,
    16,
    "1145z 24 Jan"
  ],
  "1733895777": [
    "WA7LNW",
    "14057.4",
    "KD0FNR/6",
    8,
    16,
    "1145z 24 Jan"
  ],
  "1733895646": [
    "ND7K",
    "14057.4",
    "KD0FNR/6",
    15,
    16,
    "1144z 24 Jan"
  ],
  "1733895478": [
    "VE6WZ",
    "14057.5",
    "KD0FNR/6",
    5,
    16,
    "1144z 24 Jan"
  ],
  "1733895395": [
    "W6YX",
    "14057.4",
    "KD0FNR/6",
    23,
    16,
    "1143z 24 Jan"
  ],
  "1733893907": [
    "W1NT-2",
    "14057.5",
    "KD0FNR/6",
    5,
    16,
    "1138z 24 Jan"
  ],
  "1733893452": [
    "W8WWV",
    "14057.5",
    "KD0FNR/6",
    7,
    17,
    "1136z 24 Jan"
  ],
  "1733893182": [
    "W8WWV",
    "14057.5",
    "KD0FNR",
    6,
    16,
    "1135z 24 Jan"
  ],
  "1733892888": [
    "ND7K",
    "14057.5",
    "KD0FNR/6",
    16,
    16,
    "1133z 24 Jan"
  ],
  "1733892866": [
    "WA7LNW",
    "14057.5",
    "KD0FNR/6",
    13,
    16,
    "1133z 24 Jan"
  ],
  "1733892860": [
    "W6YX",
    "14057.5",
    "KD0FNR/6",
    23,
    17,
    "1133z 24 Jan"
  ],
  "1733892853": [
    "VE6WZ",
    "14057.6",
    "KD0FNR/6",
    9,
    16,
    "1133z 24 Jan"
  ],
  "1733617037": [
    "DC8YZ",
    "28058.9",
    "KD0FNR/6",
    15,
    16,
    "1618z 23 Jan"
  ],
  "1733616861": [
    "DM6EE",
    "28058.9",
    "KD0FNR/6",
    7,
    16,
    "1617z 23 Jan"
  ],
  "1733616664": [
    "G4IRN",
    "28058.9",
    "KD0FNR/6",
    11,
    15,
    "1617z 23 Jan"
  ],
  "1733616634": [
    "WB6BEE",
    "28058.9",
    "KD0FNR/6",
    13,
    15,
    "1617z 23 Jan"
  ],
  "1733616398": [
    "W3UA",
    "28058.9",
    "KD0FNR/6",
    10,
    16,
    "1616z 23 Jan"
  ],
  "1733616368": [
    "WZ7I",
    "28058.9",
    "KD0FNR/6",
    12,
    16,
    "1616z 23 Jan"
  ],
  "1733616294": [
    "ZF9CW",
    "28058.9",
    "KD0FNR/6",
    16,
    15,
    "1616z 23 Jan"
  ],
  "1733616282": [
    "N4ZR",
    "28058.9",
    "KD0FNR/6",
    13,
    16,
    "1616z 23 Jan"
  ],
  "1733616280": [
    "KM3T-2",
    "28058.9",
    "KD0FNR/6",
    10,
    15,
    "1616z 23 Jan"
  ],
  "1733616209": [
    "TI7W",
    "28058.9",
    "KD0FNR/6",
    10,
    19,
    "1616z 23 Jan"
  ],
  "1733616205": [
    "W1NT-2",
    "28058.9",
    "KD0FNR/6",
    8,
    15,
    "1616z 23 Jan"
  ],
  "1733616040": [
    "K3PA-1",
    "28058.9",
    "KD0FNR/6",
    19,
    15,
    "1616z 23 Jan"
  ],
  "1733615997": [
    "KM3T-3",
    "28058.9",
    "KD0FNR/6",
    9,
    15,
    "1616z 23 Jan"
  ],
  "1733615989": [
    "K3PA-1",
    "28059.2",
    "KD0FNR/6",
    29,
    16,
    "1616z 23 Jan"
  ],
  "1733615963": [
    "KM3T",
    "28058.9",
    "KD0FNR/6",
    11,
    15,
    "1616z 23 Jan"
  ],
  "1733615961": [
    "W6YX",
    "28058.9",
    "KD0FNR/6",
    23,
    16,
    "1616z 23 Jan"
  ],
  "1733615920": [
    "DF2CK",
    "28058.9",
    "KD0FNR/6",
    23,
    15,
    "1616z 23 Jan"
  ],
  "1733582702": [
    "K2PO/7",
    "14057.4",
    "KD0FNR/6",
    4,
    16,
    "1507z 23 Jan"
  ],
  "1733582184": [
    "W6YX",
    "14057.4",
    "KD0FNR/6",
    15,
    16,
    "1506z 23 Jan"
  ],
  "1733582130": [
    "K3PA-1",
    "14057.4",
    "KD0FNR/6",
    11,
    16,
    "1506z 23 Jan"
  ],
  "1733582090": [
    "VE6WZ",
    "14057.5",
    "KD0FNR/6",
    7,
    16,
    "1506z 23 Jan"
  ],
  "1733582077": [
    "KO7SS",
    "14057.4",
    "KD0FNR/6",
    18,
    16,
    "1506z 23 Jan"
  ],
  "1733582063": [
    "WA7LNW",
    "14057.4",
    "KD0FNR/6",
    10,
    16,
    "1506z 23 Jan"
  ],
  "1733543000": [
    "W6YX",
    "14057.4",
    "KD0FNR/6",
    23,
    16,
    "1332z 23 Jan"
  ],
  "1733542986": [
    "W3OA",
    "14057.4",
    "KD0FNR/6",
    2,
    16,
    "1332z 23 Jan"
  ],
  "1733541294": [
    "VE6JY",
    "14057.5",
    "KD0FNR/6",
    2,
    17,
    "1327z 23 Jan"
  ],
  "1733540810": [
    "KO7SS",
    "14057.5",
    "KD0FNR/6",
    3,
    16,
    "1326z 23 Jan"
  ],
  "1733539502": [
    "VE6WZ",
    "14057.6",
    "KD0FNR/6",
    5,
    16,
    "1323z 23 Jan"
  ],
  "1733539246": [
    "W6YX",
    "14057.6",
    "KD0FNR/6",
    23,
    16,
    "1322z 23 Jan"
  ],
  "1733525492": [
    "W6YX",
    "14057.4",
    "KD0FNR/6",
    23,
    16,
    "1237z 23 Jan"
  ],
  "1733521955": [
    "W6YX",
    "14057.4",
    "KD0FNR/6",
    24,
    16,
    "1226z 23 Jan"
  ],
  "1733520877": [
    "ZF9CW",
    "14057.4",
    "KD0FNR/6",
    5,
    16,
    "1222z 23 Jan"
  ],
  "1733519197": [
    "W3OA",
    "14057.4",
    "KD0FNR",
    1,
    16,
    "1216z 23 Jan"
  ],
  "1733519196": [
    "W6YX",
    "14057.4",
    "KD0FNR/6",
    24,
    17,
    "1216z 23 Jan"
  ],
  "1733519067": [
    "ZF9CW",
    "14057.4",
    "KD0FNR/6",
    5,
    16,
    "1215z 23 Jan"
  ],
  "1733518948": [
    "W3OA",
    "14057.4",
    "KD0FNR/6",
    1,
    17,
    "1215z 23 Jan"
  ],
  "1733516911": [
    "W6YX",
    "14057.6",
    "KD0FNR/6",
    24,
    17,
    "1205z 23 Jan"
  ],
  "1733410812": [
    "WA7LNW",
    "14057.5",
    "KD0FNR/6",
    11,
    16,
    "0433z 23 Jan"
  ],
  "1733410808": [
    "VE6WZ",
    "14057.5",
    "KD0FNR/6",
    9,
    16,
    "0433z 23 Jan"
  ],
  "1733410770": [
    "K6FOD",
    "14057.5",
    "KD0FNR/6",
    9,
    16,
    "0432z 23 Jan"
  ],
  "1733410731": [
    "W6YX",
    "14057.5",
    "KD0FNR/6",
    16,
    16,
    "0432z 23 Jan"
  ],
  "1733410724": [
    "ND7K",
    "14057.5",
    "KD0FNR/6",
    18,
    16,
    "0432z 23 Jan"
  ],
  "1733410547": [
    "ND7K",
    "14058.1",
    "KD0FNR/6",
    18,
    16,
    "0429z 23 Jan"
  ],
  "1733410515": [
    "KO7SS",
    "14058.1",
    "KD0FNR/6",
    12,
    16,
    "0429z 23 Jan"
  ],
  "1733410514": [
    "W6YX",
    "14058.2",
    "KD0FNR/6",
    16,
    16,
    "0429z 23 Jan"
  ],
  "1733409268": [
    "KO7SS",
    "14058.1",
    "KD0FNR/6",
    13,
    16,
    "0415z 23 Jan"
  ],
  "1733409262": [
    "VE6JY",
    "14058.2",
    "KD0FN",
    9,
    16,
    "0415z 23 Jan"
  ],
  "1733409257": [
    "VE6WZ",
    "14058.2",
    "KD0FNR/6",
    8,
    16,
    "0415z 23 Jan"
  ],
  "1733409217": [
    "WA7LNW",
    "14058.1",
    "KD0FNR/6",
    25,
    16,
    "0414z 23 Jan"
  ],
  "1733409214": [
    "ND7K",
    "14058.1",
    "KD0FNR/6",
    18,
    16,
    "0414z 23 Jan"
  ],
  "1733409213": [
    "W6YX",
    "14058.1",
    "KD0FNR/6",
    16,
    16,
    "0414z 23 Jan"
  ],
  "1733409099": [
    "KO7SS",
    "14057.5",
    "KD0FNR/6",
    13,
    16,
    "0412z 23 Jan"
  ],
  "1733408916": [
    "VE6JY",
    "14057.6",
    "KD0FNR/6",
    8,
    16,
    "0410z 23 Jan"
  ],
  "1733408858": [
    "ND7K",
    "14057.5",
    "KD0FNR/6",
    20,
    17,
    "0409z 23 Jan"
  ],
  "1733408856": [
    "W6YX",
    "14057.5",
    "KD0FNR/6",
    16,
    16,
    "0409z 23 Jan"
  ],
  "1733408854": [
    "WA7LNW",
    "14057.5",
    "KD0FNR/6",
    28,
    17,
    "0409z 23 Jan"
  ],
  "1733359494": [
    "WC2L",
    "28059.0",
    "KD0FNR/6",
    10,
    16,
    "2330z 22 Jan"
  ],
  "1733359451": [
    "KM3T-3",
    "28059.0",
    "KD0FNR/6",
    15,
    15,
    "2330z 22 Jan"
  ],
  "1733359422": [
    "W3OA",
    "28059.0",
    "KD0FNR/6",
    14,
    15,
    "2330z 22 Jan"
  ],
  "1733359383": [
    "N4ZR",
    "28059.0",
    "KD0FNR/6",
    8,
    16,
    "2330z 22 Jan"
  ],
  "1733359284": [
    "WZ7I",
    "28059.0",
    "KD0FNR/6",
    11,
    15,
    "2329z 22 Jan"
  ],
  "1733359272": [
    "K3PA-1",
    "28059.3",
    "KD0FNR/6",
    23,
    16,
    "2329z 22 Jan"
  ],
  "1733359269": [
    "KM3T",
    "28059.0",
    "KD0FNR/6",
    17,
    16,
    "2329z 22 Jan"
  ],
  "1733359250": [
    "AC0C-1",
    "28059.0",
    "KD0FNR/6",
    8,
    15,
    "2329z 22 Jan"
  ],
  "1733359238": [
    "KM3T-2",
    "28059.0",
    "KD0FNR/6",
    16,
    16,
    "2329z 22 Jan"
  ],
  "1733359142": [
    "W1NT-6",
    "28059.0",
    "KD0FNR/6",
    8,
    16,
    "2329z 22 Jan"
  ],
  "1733359125": [
    "VE6AO",
    "28058.9",
    "KD0FNR/6",
    21,
    16,
    "2329z 22 Jan"
  ],
  "1733359109": [
    "KV4TT",
    "28059.0",
    "KD0FNR/6",
    14,
    15,
    "2329z 22 Jan"
  ],
  "1733359107": [
    "VE6JY",
    "28059.0",
    "KD0FNR/6",
    19,
    16,
    "2329z 22 Jan"
  ],
  "1733359105": [
    "KL7RA",
    "28058.9",
    "KD0FNR/6",
    19,
    15,
    "2329z 22 Jan"
  ],
  "1733359101": [
    "W8WWV",
    "28058.9",
    "KD0FNR/6",
    18,
    15,
    "2329z 22 Jan"
  ],
  "1733359099": [
    "W2NAF",
    "28059.0",
    "KD0FNR/6",
    17,
    15,
    "2329z 22 Jan"
  ],
  "1733359091": [
    "W6YX",
    "28059.0",
    "KD0FNR/6",
    27,
    16,
    "2329z 22 Jan"
  ],
  "1733359081": [
    "K1RA",
    "28058.9",
    "KD0FNR/6",
    22,
    16,
    "2329z 22 Jan"
  ],
  "1733359066": [
    "K3PA-1",
    "28059.0",
    "KD0FNR/6",
    18,
    15,
    "2329z 22 Jan"
  ],
  "1733359065": [
    "ZF9CW",
    "28059.0",
    "KD0FNR/6",
    19,
    15,
    "2329z 22 Jan"
  ],
  "1733359060": [
    "TI7W",
    "28059.0",
    "KD0FNR/6",
    16,
    19,
    "2329z 22 Jan"
  ],
  "1733099669": [
    "W6YX",
    "14057.4",
    "KD0FNR/6",
    20,
    16,
    "1347z 22 Jan"
  ],
  "1733096609": [
    "K9IMM",
    "14057.4",
    "KD0FNR/6",
    5,
    16,
    "1342z 22 Jan"
  ],
  "1733094542": [
    "VE6WZ",
    "14057.5",
    "KD0FNR/6",
    4,
    16,
    "1338z 22 Jan"
  ],
  "1733093684": [
    "W6YX",
    "14057.4",
    "KD0FNR/6",
    20,
    16,
    "1336z 22 Jan"
  ]
,
  "1734219352": [
    "ZF9CW",
    "14050.1",
    "K3Y/6",
    25,
    16,
    "2221z 24 Jan"
  ],
  "1734218178": [
    "VE6AO",
    "14050.1",
    "K3Y/6",
    14,
    16,
    "2216z 24 Jan"
  ],
  "1734217543": [
    "KL7RA",
    "14050.0",
    "K3Y/6",
    16,
    16,
    "2215z 24 Jan"
  ],
  "1734217505": [
    "W3OA",
    "14050.1",
    "K3Y/6",
    14,
    16,
    "2215z 24 Jan"
  ],
  "1734217475": [
    "K9IMM",
    "14050.1",
    "K3Y/6",
    7,
    16,
    "2214z 24 Jan"
  ],
  "1734217239": [
    "VE6WZ",
    "14050.2",
    "K3Y/6",
    25,
    16,
    "2213z 24 Jan"
  ],
  "1734217202": [
    "WA7LNW",
    "14050.1",
    "K3Y/6",
    35,
    16,
    "2213z 24 Jan"
  ],
  "1734217025": [
    "K3PA-1",
    "14050.1",
    "K3Y/6",
    15,
    16,
    "2212z 24 Jan"
  ],
  "1734216990": [
    "VE7CC",
    "14050.1",
    "K3Y/6",
    10,
    16,
    "2212z 24 Jan"
  ],
  "1734216864": [
    "NG7M",
    "14050.1",
    "K3Y/6",
    9,
    16,
    "2212z 24 Jan"
  ],
  "1734216862": [
    "K2PO/7",
    "14050.1",
    "K3Y/6",
    25,
    16,
    "2212z 24 Jan"
  ],
  "1734216859": [
    "NT6Q",
    "14050.2",
    "K3Y/6",
    23,
    17,
    "2212z 24 Jan"
  ],
  "1734216856": [
    "ND7K",
    "14050.1",
    "K3Y/6",
    17,
    16,
    "2212z 24 Jan"
  ],
  "1734216855": [
    "N7TUG",
    "14050.3",
    "K3Y/6",
    11,
    16,
    "2212z 24 Jan"
  ],
  "1734216850": [
    "VE6WZ",
    "14050.1",
    "K3Y/6",
    24,
    16,
    "2212z 24 Jan"
  ],
  "1734216847": [
    "W6YX",
    "14050.1",
    "K3Y/6",
    16,
    16,
    "2212z 24 Jan"
  ],
  "1734216832": [
    "K7RUT",
    "14050.1",
    "K3Y/6",
    15,
    16,
    "2212z 24 Jan"
  ],
  "1734216820": [
    "AC0C-1",
    "14050.1",
    "K3Y/6",
    13,
    16,
    "2212z 24 Jan"
  ],
  "1734216814": [
    "K5EM",
    "14050.1",
    "K3Y/6",
    17,
    16,
    "2212z 24 Jan"
  ],
  "1734216661": [
    "K5EM",
    "14050.1",
    "K3Y/6",
    16,
    16,
    "2211z 24 Jan"
  ],
  "1734216649": [
    "KA7OEI",
    "14050.1",
    "K3Y/6",
    42,
    16,
    "2211z 24 Jan"
  ],
  "1734216641": [
    "W3OA",
    "14050.1",
    "K3Y/6",
    15,
    17,
    "2211z 24 Jan"
  ],
  "1734216636": [
    "K6FOD",
    "14050.1",
    "K3Y/6",
    26,
    16,
    "2211z 24 Jan"
  ],
  "1734216595": [
    "WF7U",
    "14050.1",
    "K3Y/6",
    14,
    16,
    "2211z 24 Jan"
  ],
  "1734216594": [
    "VE6AO",
    "14050.1",
    "K3Y/6",
    13,
    16,
    "2211z 24 Jan"
  ],
  "1734213926": [
    "WA7LNW",
    "14050.1",
    "K3Y/6",
    32,
    15,
    "2203z 24 Jan"
  ],
  "1734213575": [
    "VE6WZ",
    "14050.1",
    "K3Y/6",
    22,
    17,
    "2202z 24 Jan"
  ],
  "1734213572": [
    "K2PO/7",
    "14050.1",
    "K3Y/6",
    24,
    17,
    "2202z 24 Jan"
  ],
  "1734213571": [
    "AC0C-1",
    "14050.1",
    "K3Y/6",
    11,
    16,
    "2202z 24 Jan"
  ],
  "1734213570": [
    "N7TUG",
    "14050.3",
    "K3Y/6",
    19,
    17,
    "2202z 24 Jan"
  ],
  "1734213568": [
    "NG7M",
    "14050.1",
    "K3Y/6",
    9,
    16,
    "2202z 24 Jan"
  ],
  "1734213539": [
    "ND7K",
    "14050.1",
    "K3Y/6",
    19,
    17,
    "2202z 24 Jan"
  ],
  "1734213536": [
    "NT6Q",
    "14050.1",
    "K3Y/6",
    27,
    16,
    "2202z 24 Jan"
  ],
  "1734213534": [
    "K3PA-1",
    "14050.1",
    "K3Y/6",
    15,
    16,
    "2202z 24 Jan"
  ],
  "1734213519": [
    "K7RUT",
    "14050.0",
    "K3Y/6",
    18,
    16,
    "2202z 24 Jan"
  ],
  "1734213515": [
    "KL7RA",
    "14050.0",
    "K3Y/6",
    18,
    16,
    "2201z 24 Jan"
  ],
  "1734213512": [
    "W6YX",
    "14050.1",
    "K3Y/6",
    16,
    16,
    "2201z 24 Jan"
  ],
  "1734212481": [
    "N9CO",
    "18089.1",
    "K3Y/6",
    20,
    16,
    "2158z 24 Jan"
  ],
  "1734212474": [
    "K3PA-1",
    "18089.1",
    "K3Y/6",
    28,
    16,
    "2157z 24 Jan"
  ],
  "1734212368": [
    "N6TV",
    "18089.1",
    "K3Y/6",
    12,
    16,
    "2157z 24 Jan"
  ],
  "1734211905": [
    "WC2L",
    "18089.1",
    "K3Y/6",
    12,
    16,
    "2155z 24 Jan"
  ],
  "1734211897": [
    "KL7RA",
    "18089.0",
    "K3Y/6",
    40,
    16,
    "2155z 24 Jan"
  ],
  "1734211896": [
    "N7TUG",
    "18089.3",
    "K3Y/6",
    25,
    17,
    "2155z 24 Jan"
  ],
  "1734211892": [
    "W3OA",
    "18089.1",
    "K3Y/6",
    18,
    16,
    "2155z 24 Jan"
  ],
  "1734211878": [
    "K5EM",
    "18089.1",
    "K3Y/6",
    22,
    16,
    "2155z 24 Jan"
  ],
  "1734211876": [
    "K4PP",
    "18089.1",
    "K3Y/6",
    17,
    16,
    "2155z 24 Jan"
  ],
  "1734211870": [
    "VE6WZ",
    "18089.1",
    "K3Y/6",
    38,
    16,
    "2155z 24 Jan"
  ],
  "1734211868": [
    "VE7CC",
    "18089.1",
    "K3Y/6",
    32,
    16,
    "2155z 24 Jan"
  ],
  "1734211587": [
    "WF7U",
    "18084.0",
    "K3Y/6",
    41,
    17,
    "2154z 24 Jan"
  ],
  "1734211397": [
    "WZ7I",
    "18088.8",
    "K3Y/6",
    21,
    16,
    "2153z 24 Jan"
  ],
  "1734210314": [
    "W3UA",
    "18084.0",
    "K3Y/6",
    12,
    16,
    "2150z 24 Jan"
  ],
  "1734210153": [
    "N6TV",
    "18084.0",
    "K3Y/6",
    12,
    16,
    "2149z 24 Jan"
  ],
  "1734210136": [
    "TI7W",
    "18084.0",
    "K3Y/6",
    17,
    20,
    "2149z 24 Jan"
  ],
  "1734210005": [
    "VE6JY",
    "18084.1",
    "K3Y/6",
    21,
    17,
    "2149z 24 Jan"
  ],
  "1734209977": [
    "WA7LNW",
    "18084.0",
    "K3Y/6",
    22,
    16,
    "2149z 24 Jan"
  ],
  "1734209972": [
    "W6YX",
    "18084.0",
    "K3Y/6",
    13,
    17,
    "2148z 24 Jan"
  ],
  "1734209875": [
    "ZF9CW",
    "18084.0",
    "K3Y/6",
    42,
    16,
    "2148z 24 Jan"
  ],
  "1734209606": [
    "W3LPL",
    "18083.9",
    "K3Y/6",
    26,
    17,
    "2147z 24 Jan"
  ],
  "1734209190": [
    "WZ7I",
    "18084.0",
    "K3Y/6",
    29,
    16,
    "2146z 24 Jan"
  ],
  "1734209165": [
    "WC2L",
    "18084.0",
    "K3Y/6",
    19,
    15,
    "2146z 24 Jan"
  ],
  "1734208771": [
    "KP3CW",
    "18084.0",
    "K3Y/6",
    16,
    16,
    "2145z 24 Jan"
  ],
  "1734208766": [
    "KL7RA",
    "18083.9",
    "K3Y/6",
    34,
    16,
    "2145z 24 Jan"
  ],
  "1734208763": [
    "JN1ILK",
    "18084.0",
    "K3Y/6",
    9,
    16,
    "2145z 24 Jan"
  ],
  "1734208761": [
    "KM3T-3",
    "18084.0",
    "K3Y/6",
    20,
    16,
    "2145z 24 Jan"
  ],
  "1734208760": [
    "W6YX",
    "18084.0",
    "K3Y/6",
    16,
    16,
    "2145z 24 Jan"
  ],
  "1734208757": [
    "K3PA-1",
    "18084.0",
    "K3Y/6",
    27,
    16,
    "2145z 24 Jan"
  ],
  "1734208750": [
    "NT6Q",
    "18084.1",
    "K3Y/6",
    18,
    16,
    "2145z 24 Jan"
  ],
  "1734208583": [
    "K9IMM",
    "18084.0",
    "K3Y/6",
    18,
    15,
    "2144z 24 Jan"
  ],
  "1734208581": [
    "W1NT-6",
    "18084.0",
    "K3Y/6",
    12,
    16,
    "2144z 24 Jan"
  ],
  "1734208572": [
    "W3OA",
    "18084.0",
    "K3Y/6",
    16,
    16,
    "2144z 24 Jan"
  ],
  "1734208563": [
    "K4PP",
    "18084.0",
    "K3Y/6",
    16,
    16,
    "2144z 24 Jan"
  ],
  "1734208559": [
    "VE7CC",
    "18084.0",
    "K3Y/6",
    31,
    16,
    "2144z 24 Jan"
  ],
  "1734208555": [
    "W8WWV",
    "18084.0",
    "K3Y/6",
    18,
    16,
    "2144z 24 Jan"
  ],
  "1734208541": [
    "ND7K",
    "18084.0",
    "K3Y/6",
    39,
    16,
    "2144z 24 Jan"
  ],
  "1734208527": [
    "N9CO",
    "18084.0",
    "K3Y/6",
    16,
    16,
    "2144z 24 Jan"
  ],
  "1734208521": [
    "K1RA",
    "18084.0",
    "K3Y/6",
    26,
    16,
    "2144z 24 Jan"
  ],
  "1734208514": [
    "VE6WZ",
    "18084.1",
    "K3Y/6",
    34,
    16,
    "2144z 24 Jan"
  ],
  "1734208509": [
    "N7TUG",
    "18084.3",
    "K3Y/6",
    20,
    16,
    "2144z 24 Jan"
  ],
  "1734208503": [
    "K5EM",
    "18084.0",
    "K3Y/6",
    21,
    16,
    "2144z 24 Jan"
  ],
  "1734208341": [
    "KM3T",
    "18084.0",
    "K3Y/6",
    22,
    16,
    "2143z 24 Jan"
  ],
  "1734207090": [
    "K9IMM",
    "18084.0",
    "K3Y/6",
    21,
    16,
    "2139z 24 Jan"
  ],
  "1734206657": [
    "ZF9CW",
    "18084.0",
    "K3Y/6",
    22,
    17,
    "2137z 24 Jan"
  ],
  "1734206173": [
    "WZ7I",
    "18084.0",
    "K3Y/6",
    19,
    16,
    "2135z 24 Jan"
  ],
  "1734205595": [
    "K4PP",
    "18083.9",
    "K3Y/6",
    15,
    16,
    "2133z 24 Jan"
  ],
  "1734205589": [
    "K5EM",
    "18083.9",
    "K3Y/6",
    20,
    16,
    "2133z 24 Jan"
  ],
  "1734205580": [
    "NT6Q",
    "18084.0",
    "K3Y/6",
    22,
    16,
    "2133z 24 Jan"
  ],
  "1734205571": [
    "N9CO",
    "18083.9",
    "K3Y/6",
    19,
    16,
    "2133z 24 Jan"
  ],
  "1734205563": [
    "K3PA-1",
    "18083.9",
    "K3Y/6",
    28,
    16,
    "2133z 24 Jan"
  ],
  "1734205562": [
    "KL7RA",
    "18083.8",
    "K3Y/6",
    29,
    16,
    "2133z 24 Jan"
  ],
  "1734205561": [
    "K1RA",
    "18083.9",
    "K3Y/6",
    22,
    17,
    "2133z 24 Jan"
  ],
  "1734205558": [
    "VE6WZ",
    "18084.0",
    "K3Y/6",
    35,
    16,
    "2133z 24 Jan"
  ],
  "1734205556": [
    "W1NT-6",
    "18083.9",
    "K3Y/6",
    13,
    16,
    "2133z 24 Jan"
  ],
  "1734205550": [
    "W3OA",
    "18083.9",
    "K3Y/6",
    20,
    16,
    "2132z 24 Jan"
  ],
  "1734205546": [
    "VE7CC",
    "18083.9",
    "K3Y/6",
    31,
    17,
    "2132z 24 Jan"
  ],
  "1734205544": [
    "WF7U",
    "18083.9",
    "K3Y/6",
    34,
    16,
    "2132z 24 Jan"
  ],
  "1734205538": [
    "N7TUG",
    "18084.1",
    "K3Y/6",
    21,
    16,
    "2132z 24 Jan"
  ],
  "1734205533": [
    "KM3T-3",
    "18083.9",
    "K3Y/6",
    19,
    16,
    "2132z 24 Jan"
  ],
  "1734205531": [
    "KM3T",
    "18083.9",
    "K3Y/6",
    19,
    16,
    "2132z 24 Jan"
  ],
  "1734205528": [
    "W3LPL",
    "18083.8",
    "K3Y/6",
    25,
    16,
    "2132z 24 Jan"
  ],
  "1734205307": [
    "ND7K",
    "18083.9",
    "K3Y/6",
    36,
    16,
    "2132z 24 Jan"
  ]
,
  "1733989884": [
    "W6YX",
    "28056.0",
    "KO6BTY",
    28,
    16,
    "1422z 24 Jan"
  ],
  "1733758621": [
    "W6YX",
    "3580.0",
    "KO6BPT",
    37,
    11,
    "0029z 24 Jan"
  ],
  "1733622258": [
    "WB6BEE",
    "28056.0",
    "KO6BTY",
    10,
    15,
    "1629z 23 Jan"
  ],
  "1733622238": [
    "W6YX",
    "28055.9",
    "KO6BTY",
    22,
    16,
    "1629z 23 Jan"
  ],
  "1731137782": [
    "W1NT-2",
    "28057.5",
    "KO6BTY",
    6,
    16,
    "1808z 20 Jan"
  ],
  "1731133759": [
    "W6YX",
    "28057.5",
    "KO6BTY",
    18,
    16,
    "1806z 20 Jan"
  ],
  "1729907176": [
    "CX6VM",
    "28057.4",
    "KO6BTY",
    4,
    16,
    "1718z 19 Jan"
  ],
  "1729905434": [
    "KM3T-3",
    "28057.5",
    "KO6BT",
    11,
    16,
    "1714z 19 Jan"
  ],
  "1729904930": [
    "W6YX",
    "28057.5",
    "KO6BTY",
    18,
    15,
    "1713z 19 Jan"
  ],
  "1729582992": [
    "W6YX",
    "28057.5",
    "KO6BTY",
    18,
    16,
    "0104z 19 Jan"
  ],
  "1729579457": [
    "W6YX",
    "28057.5",
    "KO6BTY",
    11,
    15,
    "0046z 19 Jan"
  ],
  "1727475076": [
    "W2NAF",
    "28058.0",
    "KO6BTY/6",
    9,
    15,
    "2154z 14 Jan"
  ],
  "1727475069": [
    "AC0C-1",
    "28058.0",
    "KO6BTY/6",
    10,
    16,
    "2154z 14 Jan"
  ],
  "1727475057": [
    "WB6BEE",
    "28058.0",
    "KO6BTY/6",
    16,
    16,
    "2154z 14 Jan"
  ],
  "1727475054": [
    "W1NT-2",
    "28058.0",
    "KO6BTY/6",
    11,
    15,
    "2154z 14 Jan"
  ],
  "1727474877": [
    "WC2L",
    "28058.0",
    "KO6BT",
    11,
    16,
    "2154z 14 Jan"
  ],
  "1727474760": [
    "WZ7I",
    "28058.0",
    "KO6BT",
    7,
    15,
    "2154z 14 Jan"
  ],
  "1727473460": [
    "W6YX",
    "28058.0",
    "KO6BTY/6",
    13,
    15,
    "2151z 14 Jan"
  ],
  "1727340546": [
    "WE9V",
    "28069.9",
    "KO6BTY",
    12,
    15,
    "1622z 14 Jan"
  ],
  "1727340502": [
    "N9CO",
    "28070.0",
    "KO6BTY",
    22,
    16,
    "1621z 14 Jan"
  ],
  "1727340490": [
    "K9IMM",
    "28070.0",
    "KO6BTY",
    24,
    16,
    "1621z 14 Jan"
  ],
  "1727340467": [
    "W6YX",
    "28070.0",
    "KO6BTY",
    21,
    16,
    "1621z 14 Jan"
  ],
  "1727339060": [
    "TI7W",
    "28070.0",
    "KO6BT",
    6,
    16,
    "1619z 14 Jan"
  ],
  "1727339019": [
    "W1NT-6",
    "28070.0",
    "KO6BTY",
    5,
    15,
    "1619z 14 Jan"
  ],
  "1727336764": [
    "TI7W",
    "28070.0",
    "KO6BTY",
    6,
    16,
    "1616z 14 Jan"
  ],
  "1727336411": [
    "KM3T-3",
    "28070.0",
    "KO6BTY",
    8,
    16,
    "1615z 14 Jan"
  ],
  "1727334446": [
    "W6YX",
    "28070.0",
    "KO6BTY",
    20,
    16,
    "1611z 14 Jan"
  ],
  "1724523419": [
    "W6YX",
    "3550.0",
    "KO6BPT",
    32,
    13,
    "0532z 12 Jan"
  ],
  "1724523339": [
    "K6FOD",
    "3550.0",
    "KO6BPT",
    26,
    13,
    "0532z 12 Jan"
  ],
  "1724515776": [
    "N9CO",
    "7045.0",
    "KO6BP",
    7,
    17,
    "0447z 12 Jan"
  ],
  "1682269657": [
    "S53A",
    "7026.2",
    "KO6BXE",
    37,
    18,
    "1817z 11 Nov"
  ],
  "1668887165": [
    "S53A",
    "7015.0",
    "KO6BHN",
    24,
    24,
    "0422z 19 Oct"
  ],
  "1654185288": [
    "DJ9IE",
    "7002.7",
    "KO6BHN",
    21,
    15,
    "0507z 21 Sep"
  ],
  "1654185146": [
    "W6YX",
    "7002.7",
    "KO6BHN",
    20,
    15,
    "0505z 21 Sep"
  ],
  "1654185142": [
    "DL8LAS",
    "7002.7",
    "KO6BHN",
    9,
    15,
    "0505z 21 Sep"
  ],
  "1654185138": [
    "DM5GG",
    "7002.7",
    "KO6BHN",
    15,
    15,
    "0505z 21 Sep"
  ],
  "1650895642": [
    "N6TV",
    "3577.5",
    "KO6BD",
    33,
    22,
    "0437z 13 Sep"
  ]
}
